Workbook

Sheet Resumen
A1: Plan de Proyecto – Sistema de Monitoreo CIP en Tiempo Real (MVP)
A2: Plataforma: Firebase (GCP) – Cloud Functions, Authentication, Firestore/Realtime Database, Hosting
A4: Datos generales del proyecto
A5: Fecha de inicio del MVP | B5: 46258
A6: Fecha de entrega del MVP (demo cliente) | B6: 46360
A7: Duración total | B7: 14.5 semanas (~3.3 meses) — comprimida desde el plazo original al 18-12
A8: Metodología | B8: Ágil (Scrum) – Sprints de 2 semanas
A9: N° de sprints | B9: 7 sprints de 2 semanas + 1 semana final de cierre/demo (antes eran 8 sprints + cierre)
A10: Equipo | B10: 4 desarrolladores polifuncionales + 1 técnico de hardware/maqueta
A11: Clientes objetivo del monitoreo | B11: Plantas de alimentos (ej. Soprole, Colun) que usan procesos de limpieza CIP
A12: Variables a monitorear | B12: Consumo de químicos, consumo de agua, temperatura, conductividad, pH y otras variables de sensores
A13: ⚠ Riesgo de cronograma | B13: Se mantiene el alcance completo (incluido ML predictivo) pese a tener una sprint menos; la semana de cierre ya no es un colchón real — ver pestaña Riesgos
A15: Alcance del MVP
A16: • | B16: Maqueta funcional (banco de pruebas) con sensores reales conectados: temperatura, conductividad, pH, flujo/consumo de agua y químicos.
A17: • | B17: Pipeline de ingesta de datos: sensores/gateway → Cloud Functions → Firestore/Realtime Database.
A18: • | B18: Aplicación web propia (sin herramientas externas tipo Power BI) para visualizar datos en tiempo real.
A19: • | B19: Autenticación de usuarios (Firebase Authentication) con al menos un rol de cliente y uno interno/admin.
A20: • | B20: Panel de consumo de químicos y agua provistos por la empresa, con datos históricos básicos.
A21: • | B21: Análisis predictivo con Machine Learning clásico (regresión / series de tiempo tipo ARIMA o Prophet / detección de anomalías) sobre consumo de químicos/agua y variables críticas (pH, temperatura, conductividad), entrenado con datos simulados desde el inicio y recalibrado con datos reales de la maqueta a medida que se acumulan.
A22: • | B22: Despliegue en un proyecto Firebase/GCP listo para demo ante el cliente el 04-12-2026.
A24: Fuera de alcance (post-MVP)
A25: • | B25: Reportes avanzados / exportables automatizados y alertas por correo o SMS.
A26: • | B26: Múltiples plantas/clientes en simultáneo (multi-tenant completo).
A27: • | B27: Deep learning (redes neuronales / LSTM) para el predictivo — el ML clásico entrenado con datos simulados y recalibrado con datos reales es lo que entra al MVP; modelos más sofisticados quedan como evolución post-MVP, cuando existan meses de datos reales.

Sheet Avance
A1: Avance del proyecto: plan vs. real (calculado desde 'Backlog por Sprint')
A2: Fecha de corte | B2: 46313 | C2: ← cambiar esta fecha recalcula atrasos y 'días ejecutados' en todo el libro
A3: Sprint | B3: Total | C3: Hecho | D3: En proceso | E3: Por hacer | F3: % hecho (n° actividades) | G3: Días hechos | H3: Días totales
A4: Sprint 1 | B4: =COUNTIF('Backlog por Sprint'!$A$2:$A$71,A4) | C4: =COUNTIFS('Backlog por Sprint'!$A$2:$A$71,$A4,'Backlog por Sprint'!$G$2:$G$71,"Hecho") | D4: =COUNTIFS('Backlog por Sprint'!$A$2:$A$71,$A4,'Backlog por Sprint'!$G$2:$G$71,"En proceso") | E4: =COUNTIFS('Backlog por Sprint'!$A$2:$A$71,$A4,'Backlog por Sprint'!$G$2:$G$71,"Por hacer") | F4: =IF(B4=0,0,C4/B4) | G4: =SUMIFS('Backlog por Sprint'!$E$2:$E$71,'Backlog por Sprint'!$A$2:$A$71,$A4,'Backlog por Sprint'!$G$2:$G$71,"Hecho") | H4: =SUMIF('Backlog por Sprint'!$A$2:$A$71,$A4,'Backlog por Sprint'!$E$2:$E$71)
A5: Sprint 2 | B5: =COUNTIF('Backlog por Sprint'!$A$2:$A$71,A5) | C5: =COUNTIFS('Backlog por Sprint'!$A$2:$A$71,$A5,'Backlog por Sprint'!$G$2:$G$71,"Hecho") | D5: =COUNTIFS('Backlog por Sprint'!$A$2:$A$71,$A5,'Backlog por Sprint'!$G$2:$G$71,"En proceso") | E5: =COUNTIFS('Backlog por Sprint'!$A$2:$A$71,$A5,'Backlog por Sprint'!$G$2:$G$71,"Por hacer") | F5: =IF(B5=0,0,C5/B5) | G5: =SUMIFS('Backlog por Sprint'!$E$2:$E$71,'Backlog por Sprint'!$A$2:$A$71,$A5,'Backlog por Sprint'!$G$2:$G$71,"Hecho") | H5: =SUMIF('Backlog por Sprint'!$A$2:$A$71,$A5,'Backlog por Sprint'!$E$2:$E$71)
A6: Sprint 3 | B6: =COUNTIF('Backlog por Sprint'!$A$2:$A$71,A6) | C6: =COUNTIFS('Backlog por Sprint'!$A$2:$A$71,$A6,'Backlog por Sprint'!$G$2:$G$71,"Hecho") | D6: =COUNTIFS('Backlog por Sprint'!$A$2:$A$71,$A6,'Backlog por Sprint'!$G$2:$G$71,"En proceso") | E6: =COUNTIFS('Backlog por Sprint'!$A$2:$A$71,$A6,'Backlog por Sprint'!$G$2:$G$71,"Por hacer") | F6: =IF(B6=0,0,C6/B6) | G6: =SUMIFS('Backlog por Sprint'!$E$2:$E$71,'Backlog por Sprint'!$A$2:$A$71,$A6,'Backlog por Sprint'!$G$2:$G$71,"Hecho") | H6: =SUMIF('Backlog por Sprint'!$A$2:$A$71,$A6,'Backlog por Sprint'!$E$2:$E$71)
A7: Sprint 4 | B7: =COUNTIF('Backlog por Sprint'!$A$2:$A$71,A7) | C7: =COUNTIFS('Backlog por Sprint'!$A$2:$A$71,$A7,'Backlog por Sprint'!$G$2:$G$71,"Hecho") | D7: =COUNTIFS('Backlog por Sprint'!$A$2:$A$71,$A7,'Backlog por Sprint'!$G$2:$G$71,"En proceso") | E7: =COUNTIFS('Backlog por Sprint'!$A$2:$A$71,$A7,'Backlog por Sprint'!$G$2:$G$71,"Por hacer") | F7: =IF(B7=0,0,C7/B7) | G7: =SUMIFS('Backlog por Sprint'!$E$2:$E$71,'Backlog por Sprint'!$A$2:$A$71,$A7,'Backlog por Sprint'!$G$2:$G$71,"Hecho") | H7: =SUMIF('Backlog por Sprint'!$A$2:$A$71,$A7,'Backlog por Sprint'!$E$2:$E$71)
A8: Sprint 5 | B8: =COUNTIF('Backlog por Sprint'!$A$2:$A$71,A8) | C8: =COUNTIFS('Backlog por Sprint'!$A$2:$A$71,$A8,'Backlog por Sprint'!$G$2:$G$71,"Hecho") | D8: =COUNTIFS('Backlog por Sprint'!$A$2:$A$71,$A8,'Backlog por Sprint'!$G$2:$G$71,"En proceso") | E8: =COUNTIFS('Backlog por Sprint'!$A$2:$A$71,$A8,'Backlog por Sprint'!$G$2:$G$71,"Por hacer") | F8: =IF(B8=0,0,C8/B8) | G8: =SUMIFS('Backlog por Sprint'!$E$2:$E$71,'Backlog por Sprint'!$A$2:$A$71,$A8,'Backlog por Sprint'!$G$2:$G$71,"Hecho") | H8: =SUMIF('Backlog por Sprint'!$A$2:$A$71,$A8,'Backlog por Sprint'!$E$2:$E$71)
A9: Sprint 6 | B9: =COUNTIF('Backlog por Sprint'!$A$2:$A$71,A9) | C9: =COUNTIFS('Backlog por Sprint'!$A$2:$A$71,$A9,'Backlog por Sprint'!$G$2:$G$71,"Hecho") | D9: =COUNTIFS('Backlog por Sprint'!$A$2:$A$71,$A9,'Backlog por Sprint'!$G$2:$G$71,"En proceso") | E9: =COUNTIFS('Backlog por Sprint'!$A$2:$A$71,$A9,'Backlog por Sprint'!$G$2:$G$71,"Por hacer") | F9: =IF(B9=0,0,C9/B9) | G9: =SUMIFS('Backlog por Sprint'!$E$2:$E$71,'Backlog por Sprint'!$A$2:$A$71,$A9,'Backlog por Sprint'!$G$2:$G$71,"Hecho") | H9: =SUMIF('Backlog por Sprint'!$A$2:$A$71,$A9,'Backlog por Sprint'!$E$2:$E$71)
A10: Sprint 7 | B10: =COUNTIF('Backlog por Sprint'!$A$2:$A$71,A10) | C10: =COUNTIFS('Backlog por Sprint'!$A$2:$A$71,$A10,'Backlog por Sprint'!$G$2:$G$71,"Hecho") | D10: =COUNTIFS('Backlog por Sprint'!$A$2:$A$71,$A10,'Backlog por Sprint'!$G$2:$G$71,"En proceso") | E10: =COUNTIFS('Backlog por Sprint'!$A$2:$A$71,$A10,'Backlog por Sprint'!$G$2:$G$71,"Por hacer") | F10: =IF(B10=0,0,C10/B10) | G10: =SUMIFS('Backlog por Sprint'!$E$2:$E$71,'Backlog por Sprint'!$A$2:$A$71,$A10,'Backlog por Sprint'!$G$2:$G$71,"Hecho") | H10: =SUMIF('Backlog por Sprint'!$A$2:$A$71,$A10,'Backlog por Sprint'!$E$2:$E$71)
A11: Cierre | B11: =COUNTIF('Backlog por Sprint'!$A$2:$A$71,A11) | C11: =COUNTIFS('Backlog por Sprint'!$A$2:$A$71,$A11,'Backlog por Sprint'!$G$2:$G$71,"Hecho") | D11: =COUNTIFS('Backlog por Sprint'!$A$2:$A$71,$A11,'Backlog por Sprint'!$G$2:$G$71,"En proceso") | E11: =COUNTIFS('Backlog por Sprint'!$A$2:$A$71,$A11,'Backlog por Sprint'!$G$2:$G$71,"Por hacer") | F11: =IF(B11=0,0,C11/B11) | G11: =SUMIFS('Backlog por Sprint'!$E$2:$E$71,'Backlog por Sprint'!$A$2:$A$71,$A11,'Backlog por Sprint'!$G$2:$G$71,"Hecho") | H11: =SUMIF('Backlog por Sprint'!$A$2:$A$71,$A11,'Backlog por Sprint'!$E$2:$E$71)
A12: Total | B12: =SUM(B4:B11) | C12: =SUM(C4:C11) | D12: =SUM(D4:D11) | E12: =SUM(E4:E11) | F12: =IF(B12=0,0,C12/B12) | G12: =SUM(G4:G11) | H12: =SUM(H4:H11)
A14: Por origen
A15: Plan original | B15: =COUNTIF('Backlog por Sprint'!$I$2:$I$71,"Plan original") | C15: =COUNTIFS('Backlog por Sprint'!$I$2:$I$71,"Plan original",'Backlog por Sprint'!$G$2:$G$71,"Hecho") | D15: =COUNTIFS('Backlog por Sprint'!$I$2:$I$71,"Plan original",'Backlog por Sprint'!$G$2:$G$71,"En proceso") | E15: =COUNTIFS('Backlog por Sprint'!$I$2:$I$71,"Plan original",'Backlog por Sprint'!$G$2:$G$71,"Por hacer") | F15: =IF(B15=0,0,C15/B15) | G15: =SUMIFS('Backlog por Sprint'!$E$2:$E$71,'Backlog por Sprint'!$I$2:$I$71,"Plan original",'Backlog por Sprint'!$G$2:$G$71,"Hecho") | H15: =SUMIF('Backlog por Sprint'!$I$2:$I$71,"Plan original",'Backlog por Sprint'!$E$2:$E$71)
A16: Agregadas (no planificadas) | B16: =COUNTIF('Backlog por Sprint'!$I$2:$I$71,"Agregada*") | C16: =COUNTIFS('Backlog por Sprint'!$I$2:$I$71,"Agregada*",'Backlog por Sprint'!$G$2:$G$71,"Hecho") | D16: =COUNTIFS('Backlog por Sprint'!$I$2:$I$71,"Agregada*",'Backlog por Sprint'!$G$2:$G$71,"En proceso") | E16: =COUNTIFS('Backlog por Sprint'!$I$2:$I$71,"Agregada*",'Backlog por Sprint'!$G$2:$G$71,"Por hacer") | F16: =IF(B16=0,0,C16/B16) | G16: =SUMIFS('Backlog por Sprint'!$E$2:$E$71,'Backlog por Sprint'!$I$2:$I$71,"Agregada*",'Backlog por Sprint'!$G$2:$G$71,"Hecho") | H16: =SUMIF('Backlog por Sprint'!$I$2:$I$71,"Agregada*",'Backlog por Sprint'!$E$2:$E$71)
A18: Notas:
A19: • Estados actualizados según evidencia en el repositorio (ramas feature/HL, CR, main) y lo informado por el equipo el 18-10-2026.
A20: • La maqueta física y la recepción de sensores no se pueden verificar en git: se registran según lo indicado por el equipo.
A21: • Días de las actividades agregadas: estimación retroactiva (ver nota al final de 'Backlog por Sprint').
A22: • Fuentes de estados: Aplicación/stormcip/SPRINT3.md, Base de datos/PENDIENTES-DASHBOARD.md y el historial de commits.
A24: Contraste de plazos: actividades del plan original
A25: Sprint | B25: Fin plan | C25: Actividades | D25: Hechas a tiempo | E25: Hechas con atraso | F25: Hechas sin fecha | G25: Pendientes atrasadas | H25: Pendientes en plazo | I25: Mayor atraso (días) | J25: Mayor atraso (semanas)
A26: Sprint 1 | B26: =INDEX('Roadmap Sprints'!$C$2:$C$9,MATCH(IF(A26="Cierre","Semana de cierre",A26),'Roadmap Sprints'!$A$2:$A$9,0)) | C26: =COUNTIFS('Backlog por Sprint'!$A$2:$A$71,$A26,'Backlog por Sprint'!$I$2:$I$71,"Plan original") | D26: =COUNTIFS('Backlog por Sprint'!$A$2:$A$71,$A26,'Backlog por Sprint'!$Q$2:$Q$71,"Hecha a tiempo") | E26: =COUNTIFS('Backlog por Sprint'!$A$2:$A$71,$A26,'Backlog por Sprint'!$Q$2:$Q$71,"Hecha con atraso") | F26: =COUNTIFS('Backlog por Sprint'!$A$2:$A$71,$A26,'Backlog por Sprint'!$Q$2:$Q$71,"Hecha (sin fecha)") | G26: =COUNTIFS('Backlog por Sprint'!$A$2:$A$71,$A26,'Backlog por Sprint'!$Q$2:$Q$71,"Pendiente atrasada") | H26: =COUNTIFS('Backlog por Sprint'!$A$2:$A$71,$A26,'Backlog por Sprint'!$Q$2:$Q$71,"Pendiente en plazo") | I26: =MAX(0,_xlfn.MAXIFS('Backlog por Sprint'!$O$2:$O$71,'Backlog por Sprint'!$A$2:$A$71,$A26,'Backlog por Sprint'!$I$2:$I$71,"Plan original")) | J26: =ROUND(I26/7,1)
A27: Sprint 2 | B27: =INDEX('Roadmap Sprints'!$C$2:$C$9,MATCH(IF(A27="Cierre","Semana de cierre",A27),'Roadmap Sprints'!$A$2:$A$9,0)) | C27: =COUNTIFS('Backlog por Sprint'!$A$2:$A$71,$A27,'Backlog por Sprint'!$I$2:$I$71,"Plan original") | D27: =COUNTIFS('Backlog por Sprint'!$A$2:$A$71,$A27,'Backlog por Sprint'!$Q$2:$Q$71,"Hecha a tiempo") | E27: =COUNTIFS('Backlog por Sprint'!$A$2:$A$71,$A27,'Backlog por Sprint'!$Q$2:$Q$71,"Hecha con atraso") | F27: =COUNTIFS('Backlog por Sprint'!$A$2:$A$71,$A27,'Backlog por Sprint'!$Q$2:$Q$71,"Hecha (sin fecha)") | G27: =COUNTIFS('Backlog por Sprint'!$A$2:$A$71,$A27,'Backlog por Sprint'!$Q$2:$Q$71,"Pendiente atrasada") | H27: =COUNTIFS('Backlog por Sprint'!$A$2:$A$71,$A27,'Backlog por Sprint'!$Q$2:$Q$71,"Pendiente en plazo") | I27: =MAX(0,_xlfn.MAXIFS('Backlog por Sprint'!$O$2:$O$71,'Backlog por Sprint'!$A$2:$A$71,$A27,'Backlog por Sprint'!$I$2:$I$71,"Plan original")) | J27: =ROUND(I27/7,1)
A28: Sprint 3 | B28: =INDEX('Roadmap Sprints'!$C$2:$C$9,MATCH(IF(A28="Cierre","Semana de cierre",A28),'Roadmap Sprints'!$A$2:$A$9,0)) | C28: =COUNTIFS('Backlog por Sprint'!$A$2:$A$71,$A28,'Backlog por Sprint'!$I$2:$I$71,"Plan original") | D28: =COUNTIFS('Backlog por Sprint'!$A$2:$A$71,$A28,'Backlog por Sprint'!$Q$2:$Q$71,"Hecha a tiempo") | E28: =COUNTIFS('Backlog por Sprint'!$A$2:$A$71,$A28,'Backlog por Sprint'!$Q$2:$Q$71,"Hecha con atraso") | F28: =COUNTIFS('Backlog por Sprint'!$A$2:$A$71,$A28,'Backlog por Sprint'!$Q$2:$Q$71,"Hecha (sin fecha)") | G28: =COUNTIFS('Backlog por Sprint'!$A$2:$A$71,$A28,'Backlog por Sprint'!$Q$2:$Q$71,"Pendiente atrasada") | H28: =COUNTIFS('Backlog por Sprint'!$A$2:$A$71,$A28,'Backlog por Sprint'!$Q$2:$Q$71,"Pendiente en plazo") | I28: =MAX(0,_xlfn.MAXIFS('Backlog por Sprint'!$O$2:$O$71,'Backlog por Sprint'!$A$2:$A$71,$A28,'Backlog por Sprint'!$I$2:$I$71,"Plan original")) | J28: =ROUND(I28/7,1)
A29: Sprint 4 | B29: =INDEX('Roadmap Sprints'!$C$2:$C$9,MATCH(IF(A29="Cierre","Semana de cierre",A29),'Roadmap Sprints'!$A$2:$A$9,0)) | C29: =COUNTIFS('Backlog por Sprint'!$A$2:$A$71,$A29,'Backlog por Sprint'!$I$2:$I$71,"Plan original") | D29: =COUNTIFS('Backlog por Sprint'!$A$2:$A$71,$A29,'Backlog por Sprint'!$Q$2:$Q$71,"Hecha a tiempo") | E29: =COUNTIFS('Backlog por Sprint'!$A$2:$A$71,$A29,'Backlog por Sprint'!$Q$2:$Q$71,"Hecha con atraso") | F29: =COUNTIFS('Backlog por Sprint'!$A$2:$A$71,$A29,'Backlog por Sprint'!$Q$2:$Q$71,"Hecha (sin fecha)") | G29: =COUNTIFS('Backlog por Sprint'!$A$2:$A$71,$A29,'Backlog por Sprint'!$Q$2:$Q$71,"Pendiente atrasada") | H29: =COUNTIFS('Backlog por Sprint'!$A$2:$A$71,$A29,'Backlog por Sprint'!$Q$2:$Q$71,"Pendiente en plazo") | I29: =MAX(0,_xlfn.MAXIFS('Backlog por Sprint'!$O$2:$O$71,'Backlog por Sprint'!$A$2:$A$71,$A29,'Backlog por Sprint'!$I$2:$I$71,"Plan original")) | J29: =ROUND(I29/7,1)
A30: Sprint 5 | B30: =INDEX('Roadmap Sprints'!$C$2:$C$9,MATCH(IF(A30="Cierre","Semana de cierre",A30),'Roadmap Sprints'!$A$2:$A$9,0)) | C30: =COUNTIFS('Backlog por Sprint'!$A$2:$A$71,$A30,'Backlog por Sprint'!$I$2:$I$71,"Plan original") | D30: =COUNTIFS('Backlog por Sprint'!$A$2:$A$71,$A30,'Backlog por Sprint'!$Q$2:$Q$71,"Hecha a tiempo") | E30: =COUNTIFS('Backlog por Sprint'!$A$2:$A$71,$A30,'Backlog por Sprint'!$Q$2:$Q$71,"Hecha con atraso") | F30: =COUNTIFS('Backlog por Sprint'!$A$2:$A$71,$A30,'Backlog por Sprint'!$Q$2:$Q$71,"Hecha (sin fecha)") | G30: =COUNTIFS('Backlog por Sprint'!$A$2:$A$71,$A30,'Backlog por Sprint'!$Q$2:$Q$71,"Pendiente atrasada") | H30: =COUNTIFS('Backlog por Sprint'!$A$2:$A$71,$A30,'Backlog por Sprint'!$Q$2:$Q$71,"Pendiente en plazo") | I30: =MAX(0,_xlfn.MAXIFS('Backlog por Sprint'!$O$2:$O$71,'Backlog por Sprint'!$A$2:$A$71,$A30,'Backlog por Sprint'!$I$2:$I$71,"Plan original")) | J30: =ROUND(I30/7,1)
A31: Sprint 6 | B31: =INDEX('Roadmap Sprints'!$C$2:$C$9,MATCH(IF(A31="Cierre","Semana de cierre",A31),'Roadmap Sprints'!$A$2:$A$9,0)) | C31: =COUNTIFS('Backlog por Sprint'!$A$2:$A$71,$A31,'Backlog por Sprint'!$I$2:$I$71,"Plan original") | D31: =COUNTIFS('Backlog por Sprint'!$A$2:$A$71,$A31,'Backlog por Sprint'!$Q$2:$Q$71,"Hecha a tiempo") | E31: =COUNTIFS('Backlog por Sprint'!$A$2:$A$71,$A31,'Backlog por Sprint'!$Q$2:$Q$71,"Hecha con atraso") | F31: =COUNTIFS('Backlog por Sprint'!$A$2:$A$71,$A31,'Backlog por Sprint'!$Q$2:$Q$71,"Hecha (sin fecha)") | G31: =COUNTIFS('Backlog por Sprint'!$A$2:$A$71,$A31,'Backlog por Sprint'!$Q$2:$Q$71,"Pendiente atrasada") | H31: =COUNTIFS('Backlog por Sprint'!$A$2:$A$71,$A31,'Backlog por Sprint'!$Q$2:$Q$71,"Pendiente en plazo") | I31: =MAX(0,_xlfn.MAXIFS('Backlog por Sprint'!$O$2:$O$71,'Backlog por Sprint'!$A$2:$A$71,$A31,'Backlog por Sprint'!$I$2:$I$71,"Plan original")) | J31: =ROUND(I31/7,1)
A32: Sprint 7 | B32: =INDEX('Roadmap Sprints'!$C$2:$C$9,MATCH(IF(A32="Cierre","Semana de cierre",A32),'Roadmap Sprints'!$A$2:$A$9,0)) | C32: =COUNTIFS('Backlog por Sprint'!$A$2:$A$71,$A32,'Backlog por Sprint'!$I$2:$I$71,"Plan original") | D32: =COUNTIFS('Backlog por Sprint'!$A$2:$A$71,$A32,'Backlog por Sprint'!$Q$2:$Q$71,"Hecha a tiempo") | E32: =COUNTIFS('Backlog por Sprint'!$A$2:$A$71,$A32,'Backlog por Sprint'!$Q$2:$Q$71,"Hecha con atraso") | F32: =COUNTIFS('Backlog por Sprint'!$A$2:$A$71,$A32,'Backlog por Sprint'!$Q$2:$Q$71,"Hecha (sin fecha)") | G32: =COUNTIFS('Backlog por Sprint'!$A$2:$A$71,$A32,'Backlog por Sprint'!$Q$2:$Q$71,"Pendiente atrasada") | H32: =COUNTIFS('Backlog por Sprint'!$A$2:$A$71,$A32,'Backlog por Sprint'!$Q$2:$Q$71,"Pendiente en plazo") | I32: =MAX(0,_xlfn.MAXIFS('Backlog por Sprint'!$O$2:$O$71,'Backlog por Sprint'!$A$2:$A$71,$A32,'Backlog por Sprint'!$I$2:$I$71,"Plan original")) | J32: =ROUND(I32/7,1)
A33: Cierre | B33: =INDEX('Roadmap Sprints'!$C$2:$C$9,MATCH(IF(A33="Cierre","Semana de cierre",A33),'Roadmap Sprints'!$A$2:$A$9,0)) | C33: =COUNTIFS('Backlog por Sprint'!$A$2:$A$71,$A33,'Backlog por Sprint'!$I$2:$I$71,"Plan original") | D33: =COUNTIFS('Backlog por Sprint'!$A$2:$A$71,$A33,'Backlog por Sprint'!$Q$2:$Q$71,"Hecha a tiempo") | E33: =COUNTIFS('Backlog por Sprint'!$A$2:$A$71,$A33,'Backlog por Sprint'!$Q$2:$Q$71,"Hecha con atraso") | F33: =COUNTIFS('Backlog por Sprint'!$A$2:$A$71,$A33,'Backlog por Sprint'!$Q$2:$Q$71,"Hecha (sin fecha)") | G33: =COUNTIFS('Backlog por Sprint'!$A$2:$A$71,$A33,'Backlog por Sprint'!$Q$2:$Q$71,"Pendiente atrasada") | H33: =COUNTIFS('Backlog por Sprint'!$A$2:$A$71,$A33,'Backlog por Sprint'!$Q$2:$Q$71,"Pendiente en plazo") | I33: =MAX(0,_xlfn.MAXIFS('Backlog por Sprint'!$O$2:$O$71,'Backlog por Sprint'!$A$2:$A$71,$A33,'Backlog por Sprint'!$I$2:$I$71,"Plan original")) | J33: =ROUND(I33/7,1)
A34: Total | C34: =SUM(C26:C33) | D34: =SUM(D26:D33) | E34: =SUM(E26:E33) | F34: =SUM(F26:F33) | G34: =SUM(G26:G33) | H34: =SUM(H26:H33) | I34: =MAX(I26:I33) | J34: =ROUND(I34/7,1)
A36: Cumplimiento a la fecha de corte (solo plan original)
A37: Indicador | B37: Actividades | C37: Días-persona
A38: Con vencimiento hasta el corte (debían estar hechas) | B38: =COUNTIFS('Backlog por Sprint'!$I$2:$I$71,"Plan original",'Backlog por Sprint'!$K$2:$K$71,"<="&Avance!$B$2) | C38: =SUMIFS('Backlog por Sprint'!$E$2:$E$71,'Backlog por Sprint'!$I$2:$I$71,"Plan original",'Backlog por Sprint'!$K$2:$K$71,"<="&Avance!$B$2)
A39: de ellas, hechas | B39: =COUNTIFS('Backlog por Sprint'!$I$2:$I$71,"Plan original",'Backlog por Sprint'!$K$2:$K$71,"<="&Avance!$B$2,'Backlog por Sprint'!$G$2:$G$71,"Hecho") | C39: =SUMIFS('Backlog por Sprint'!$E$2:$E$71,'Backlog por Sprint'!$I$2:$I$71,"Plan original",'Backlog por Sprint'!$K$2:$K$71,"<="&Avance!$B$2,'Backlog por Sprint'!$G$2:$G$71,"Hecho")
A40: de ellas, en proceso | B40: =COUNTIFS('Backlog por Sprint'!$I$2:$I$71,"Plan original",'Backlog por Sprint'!$K$2:$K$71,"<="&Avance!$B$2,'Backlog por Sprint'!$G$2:$G$71,"En proceso") | C40: =SUMIFS('Backlog por Sprint'!$E$2:$E$71,'Backlog por Sprint'!$I$2:$I$71,"Plan original",'Backlog por Sprint'!$K$2:$K$71,"<="&Avance!$B$2,'Backlog por Sprint'!$G$2:$G$71,"En proceso")
A41: de ellas, por hacer | B41: =B38-B39-B40 | C41: =C38-C39-C40
A42: Cumplimiento de lo comprometido (hechas / con vencimiento) | B42: =IF(B38=0,0,B39/B38) | C42: =IF(C38=0,0,C39/C38)
A43: Tiempo transcurrido del proyecto (inicio a demo) | B43: =(Avance!$B$2-'Roadmap Sprints'!$B$2+1)/('Roadmap Sprints'!$C$9-'Roadmap Sprints'!$B$2+1)
A44: Semanas transcurridas / semanas totales | B44: =ROUND((Avance!$B$2-'Roadmap Sprints'!$B$2+1)/7,1) | C44: =ROUND(('Roadmap Sprints'!$C$9-'Roadmap Sprints'!$B$2+1)/7,1)
A45: Trabajo no planificado hecho (agregadas, días retroactivos) | B45: =COUNTIFS('Backlog por Sprint'!$I$2:$I$71,"Agregada*",'Backlog por Sprint'!$G$2:$G$71,"Hecho") | C45: =SUMIFS('Backlog por Sprint'!$E$2:$E$71,'Backlog por Sprint'!$I$2:$I$71,"Agregada*",'Backlog por Sprint'!$G$2:$G$71,"Hecho")
A46: Días-persona del plan aún por entregar (no hechas) | B46: =COUNTIFS('Backlog por Sprint'!$I$2:$I$71,"Plan original",'Backlog por Sprint'!$G$2:$G$71,"<>Hecho") | C46: =SUMIFS('Backlog por Sprint'!$E$2:$E$71,'Backlog por Sprint'!$I$2:$I$71,"Plan original",'Backlog por Sprint'!$G$2:$G$71,"<>Hecho")
A47: Semanas que faltan hasta la demo | B47: =ROUND(('Roadmap Sprints'!$C$9-Avance!$B$2)/7,1)

Sheet Roadmap Sprints
A1: Sprint | B1: Inicio | C1: Fin | D1: Días hábiles | E1: Objetivo principal del sprint | F1: Hito / Entregable clave | G1: Foco del Técnico (maqueta)
A2: Sprint 1 | B2: 46258 | C2: 46271 | D2: =NETWORKDAYS(B2,C2) | E2: Descubrimiento, arquitectura y cotización. Definir backlog completo, levantar requerimientos con el cliente, diseñar arquitectura Firebase (Auth, Firestore/Realtime DB, Functions) y dejar lista la infraestructura base (proyecto GCP, repos, CI). En paralelo, diseñar el enfoque de simulación de datos para el módulo de ML predictivo (qué variables, qué patrones física-informados usar). | F2: Backlog priorizado + arquitectura aprobada + proyecto Firebase creado + diseño de la simulación de datos | G2: Terminar cotización de sensores/gateway; definir modelo de sensores a comprar
A3: Sprint 2 | B3: 46272 | C3: 46285 | D3: =NETWORKDAYS(B3,C3) | E3: Compra de sensores y arranque de desarrollo base. Gestionar compra/OC de sensores y gateway. Implementar Firebase Authentication y esquema de datos (Firestore) para lecturas de sensores. Generar el dataset simulado y entrenar la primera versión de los modelos de ML clásico (regresión / ARIMA-Prophet) con esos datos sintéticos. | F3: Sensores comprados (OC emitida) + Auth funcional + esquema de datos definido + primer modelo ML entrenado con datos simulados | G3: Recepción de sensores, pruebas de conexión básicas en banco (sin maqueta aún)
A4: Sprint 3 | B4: 46286 | C4: 46299 | D4: =NETWORKDAYS(B4,C4) | E4: Ingesta de datos y esqueleto de maqueta. Construir Cloud Functions que reciban datos de sensores y los escriban en la base de datos en tiempo real. Iniciar armado físico de la maqueta. Integrar el modelo ML (entrenado con datos simulados) al backend, exponiendo predicciones vía Function. | F4: Pipeline sensor → Function → Firestore funcionando con datos simulados + modelo ML servido desde el backend | G4: Armado estructural de la maqueta y montaje de sensores
A5: Sprint 4 | B5: 46300 | C5: 46313 | D5: =NETWORKDAYS(B5,C5) | E5: Primer end-to-end con datos reales. Maqueta enviando datos reales de al menos 2 sensores (ej. temperatura y pH). Construir el esqueleto del dashboard web con gráficos en tiempo real, incluyendo un primer panel con la proyección del modelo ML (aún entrenado solo con datos simulados). | F5: Demo interna: datos reales de la maqueta llegando al dashboard en vivo + primer panel predictivo visible | G5: Maqueta operativa con sensores críticos conectados y calibrados
A6: Sprint 5 | B6: 46314 | C6: 46327 | D6: =NETWORKDAYS(B6,C6) | E6: Visualización completa. Integrar todos los sensores (conductividad, consumo de agua, químicos). Construir vistas de consumo de químicos/agua y series históricas básicas. Empezar a recalibrar los modelos de ML con los primeros datos reales que ya entrega la maqueta. | F6: Dashboard muestra todas las variables clave en tiempo real + históricos + modelo ML empezando a usar datos reales | G6: Todos los sensores de la maqueta integrados y estables
A7: Sprint 6 | B7: 46328 | C7: 46341 | D7: =NETWORKDAYS(B7,C7) | E7: Roles, seguridad y robustez. Implementar roles de usuario (cliente/interno) y reglas de seguridad de Firestore. Manejo de errores, reconexión de sensores y pérdida de datos. Validar la precisión del modelo ML contra los datos reales acumulados y pulir el panel predictivo en el dashboard. | F7: Reglas de seguridad + control de acceso por rol + manejo de desconexiones + modelo ML validado con datos reales | G7: Pruebas de estabilidad de la maqueta en jornadas prolongadas (esto también alimenta el histórico real)
A8: Sprint 7 | B8: 46342 | C8: 46355 | D8: =NETWORKDAYS(B8,C8) | E8: Pruebas integrales y cierre técnico. Testing end-to-end, pruebas de carga con flujo continuo de datos, corrección de bugs, documentación técnica y de usuario, despliegue a ambiente estable. Pruebas de aceptación interna (UAT) y preparación del guion de demo, incluido el panel de ML predictivo. | F8: Ambiente de staging/producción estable y probado + MVP completo listo para UAT | G8: Ajustes finales de calibración, confiabilidad de sensores y preparación para transporte
A9: Semana de cierre | B9: 46356 | C9: 46360 | D9: =NETWORKDAYS(B9,C9) | E9: Semana de cierre y presentación. Buffer para imprevistos, corrección de bugs críticos de última hora, ensayo general con el equipo completo y presentación del MVP al cliente. Esta semana ya no tiene holgura extra: es el único colchón que queda si algo del cronograma se atrasó. | F9: Presentación del MVP al cliente (04-12-2026) | G9: Puesta a punto de la maqueta el día de la demo
A11: Nota: 'Días hábiles' se calcula con NETWORKDAYS y no descuenta feriados chilenos; ajustar manualmente si corresponde.

Sheet Historias de usuario
A1: Product Backlog: historias de usuario (requisitos funcionales) y habilitadores
A2: BORRADOR propuesto el 19-10-2026 a partir de las tareas del backlog; el equipo debe revisar redacción, criterios y prioridad. El avance se calcula desde las tareas vinculadas (columna 'Historia (ID)' del backlog).
A4: ID | B4: Tipo | C4: Historia de usuario / descripción | D4: Criterios de aceptación | E4: Prioridad | F4: Tareas | G4: Hechas | H4: En proceso | I4: Avance | J4: Estado
A5: HU-01 | B5: Historia de usuario | C5: Como operador, quiero ver en tiempo real el pH, la conductividad y la temperatura del ciclo en curso, para saber cómo avanza la limpieza. | D5: 1) Cada lectura nueva aparece en el dashboard sin recargar la página. 2) Cada tarjeta muestra valor, unidad y hora de la lectura. 3) Si una sonda no reporta o está saturada, la tarjeta lo indica en vez de mostrar un valor. | E5: Alta | F5: =COUNTIF('Backlog por Sprint'!$R$2:$R$71,A5) | G5: =COUNTIFS('Backlog por Sprint'!$R$2:$R$71,A5,'Backlog por Sprint'!$G$2:$G$71,"Hecho") | H5: =COUNTIFS('Backlog por Sprint'!$R$2:$R$71,A5,'Backlog por Sprint'!$G$2:$G$71,"En proceso") | I5: =IF(F5=0,0,G5/F5) | J5: =IF(F5=0,"Sin tareas",IF(G5=F5,"Hecha",IF(G5+H5>0,"En proceso","Por hacer")))
A6: HU-02 | B6: Historia de usuario | C6: Como operador, quiero ver en qué etapa del CIP está el ciclo y cuánto tiempo lleva, para coordinar la operación. | D6: 1) La barra muestra las etapas en orden y marca la actual. 2) Se ve el tiempo transcurrido de la etapa. 3) Las etapas fuera del alcance de las sondas se señalan como no monitoreadas. | E6: Media | F6: =COUNTIF('Backlog por Sprint'!$R$2:$R$71,A6) | G6: =COUNTIFS('Backlog por Sprint'!$R$2:$R$71,A6,'Backlog por Sprint'!$G$2:$G$71,"Hecho") | H6: =COUNTIFS('Backlog por Sprint'!$R$2:$R$71,A6,'Backlog por Sprint'!$G$2:$G$71,"En proceso") | I6: =IF(F6=0,0,G6/F6) | J6: =IF(F6=0,"Sin tareas",IF(G6=F6,"Hecha",IF(G6+H6>0,"En proceso","Por hacer")))
A7: HU-03 | B7: Historia de usuario | C7: Como operador, quiero recibir una alerta cuando una variable sale del rango de la etapa, para corregir a tiempo. | D7: 1) Una lectura fuera del umbral de su etapa crea una alerta con variable, valor, rango y hora. 2) Si la red reintenta el mismo mensaje no se duplica la alerta. 3) El historial de alertas queda visible en el dashboard. | E7: Alta | F7: =COUNTIF('Backlog por Sprint'!$R$2:$R$71,A7) | G7: =COUNTIFS('Backlog por Sprint'!$R$2:$R$71,A7,'Backlog por Sprint'!$G$2:$G$71,"Hecho") | H7: =COUNTIFS('Backlog por Sprint'!$R$2:$R$71,A7,'Backlog por Sprint'!$G$2:$G$71,"En proceso") | I7: =IF(F7=0,0,G7/F7) | J7: =IF(F7=0,"Sin tareas",IF(G7=F7,"Hecha",IF(G7+H7>0,"En proceso","Por hacer")))
A8: HU-04 | B8: Historia de usuario | C8: Como jefe de producción, quiero ver el historial de las últimas 24 horas y 7 días por variable, para comparar ciclos. | D8: 1) Se puede elegir la variable y el período (24 h o 7 días). 2) El gráfico muestra las lecturas de todos los ciclos del período. 3) Funciona con el índice de lecturas desplegado. | E8: Media | F8: =COUNTIF('Backlog por Sprint'!$R$2:$R$71,A8) | G8: =COUNTIFS('Backlog por Sprint'!$R$2:$R$71,A8,'Backlog por Sprint'!$G$2:$G$71,"Hecho") | H8: =COUNTIFS('Backlog por Sprint'!$R$2:$R$71,A8,'Backlog por Sprint'!$G$2:$G$71,"En proceso") | I8: =IF(F8=0,0,G8/F8) | J8: =IF(F8=0,"Sin tareas",IF(G8=F8,"Hecha",IF(G8+H8>0,"En proceso","Por hacer")))
A9: HU-05 | B9: Historia de usuario | C9: Como jefe de producción, quiero ver el consumo de agua y de químicos de cada ciclo, para optimizar recursos. | D9: 1) El consumo de agua se calcula desde el flujómetro cuando existe. 2) Si el valor es estimado (caudal nominal) se marca como estimado. 3) Se ve el total por ciclo y su tendencia. | E9: Media | F9: =COUNTIF('Backlog por Sprint'!$R$2:$R$71,A9) | G9: =COUNTIFS('Backlog por Sprint'!$R$2:$R$71,A9,'Backlog por Sprint'!$G$2:$G$71,"Hecho") | H9: =COUNTIFS('Backlog por Sprint'!$R$2:$R$71,A9,'Backlog por Sprint'!$G$2:$G$71,"En proceso") | I9: =IF(F9=0,0,G9/F9) | J9: =IF(F9=0,"Sin tareas",IF(G9=F9,"Hecha",IF(G9+H9>0,"En proceso","Por hacer")))
A10: HU-06 | B10: Historia de usuario | C10: Como jefe de producción, quiero ver indicadores al cerrar un ciclo, para evaluar si la limpieza fue eficiente. | D10: 1) Al finalizar un ciclo se calculan tiempo hasta agua limpia, arrastre químico, pendiente de conductividad y volumen. 2) Cada indicador muestra su método y si es medido o estimado. 3) Un ciclo sin datos útiles explica el motivo. | E10: Alta | F10: =COUNTIF('Backlog por Sprint'!$R$2:$R$71,A10) | G10: =COUNTIFS('Backlog por Sprint'!$R$2:$R$71,A10,'Backlog por Sprint'!$G$2:$G$71,"Hecho") | H10: =COUNTIFS('Backlog por Sprint'!$R$2:$R$71,A10,'Backlog por Sprint'!$G$2:$G$71,"En proceso") | I10: =IF(F10=0,0,G10/F10) | J10: =IF(F10=0,"Sin tareas",IF(G10=F10,"Hecha",IF(G10+H10>0,"En proceso","Por hacer")))
A11: HU-07 | B11: Historia de usuario | C11: Como jefe de producción, quiero una proyección de cuándo quedará limpio el enjuague y avisos de tendencias anómalas, para anticipar problemas. | D11: 1) El dashboard muestra una proyección en minutos con su nivel de confianza. 2) Se avisa cuando una variable tiende a salir de rango. 3) El modelo se valida contra datos reales de la maqueta antes de la demo. | E11: Alta | F11: =COUNTIF('Backlog por Sprint'!$R$2:$R$71,A11) | G11: =COUNTIFS('Backlog por Sprint'!$R$2:$R$71,A11,'Backlog por Sprint'!$G$2:$G$71,"Hecho") | H11: =COUNTIFS('Backlog por Sprint'!$R$2:$R$71,A11,'Backlog por Sprint'!$G$2:$G$71,"En proceso") | I11: =IF(F11=0,0,G11/F11) | J11: =IF(F11=0,"Sin tareas",IF(G11=F11,"Hecha",IF(G11+H11>0,"En proceso","Por hacer")))
A12: HU-08 | B12: Historia de usuario | C12: Como usuario, quiero iniciar sesión y ver solo lo que mi rol permite, para proteger la información de la planta. | D12: 1) Sin sesión no se accede al dashboard. 2) Admin, operador y visor ven y modifican solo lo que su rol permite, también a nivel de base de datos. 3) Las reglas se prueban con tests automáticos. | E12: Alta | F12: =COUNTIF('Backlog por Sprint'!$R$2:$R$71,A12) | G12: =COUNTIFS('Backlog por Sprint'!$R$2:$R$71,A12,'Backlog por Sprint'!$G$2:$G$71,"Hecho") | H12: =COUNTIFS('Backlog por Sprint'!$R$2:$R$71,A12,'Backlog por Sprint'!$G$2:$G$71,"En proceso") | I12: =IF(F12=0,0,G12/F12) | J12: =IF(F12=0,"Sin tareas",IF(G12=F12,"Hecha",IF(G12+H12>0,"En proceso","Por hacer")))
A13: HU-09 | B13: Historia de usuario | C13: Como administrador, quiero asignar roles a los usuarios, para controlar quién accede a qué. | D13: 1) Solo un admin puede cambiar un rol. 2) Un usuario nuevo parte como visor. 3) El cambio se refleja al volver a iniciar sesión. | E13: Media | F13: =COUNTIF('Backlog por Sprint'!$R$2:$R$71,A13) | G13: =COUNTIFS('Backlog por Sprint'!$R$2:$R$71,A13,'Backlog por Sprint'!$G$2:$G$71,"Hecho") | H13: =COUNTIFS('Backlog por Sprint'!$R$2:$R$71,A13,'Backlog por Sprint'!$G$2:$G$71,"En proceso") | I13: =IF(F13=0,0,G13/F13) | J13: =IF(F13=0,"Sin tareas",IF(G13=F13,"Hecha",IF(G13+H13>0,"En proceso","Por hacer")))
A14: HU-10 | B14: Historia de usuario | C14: Como administrador, quiero ver el estado de cada equipo (firmware, batería y última señal), para detectar sensores con problemas. | D14: 1) Se ve el firmware registrado y el reportado por el equipo. 2) Se ve la batería y la hora de la última señal y de la última medición. 3) Se avisa si un equipo deja de medir durante un ciclo. | E14: Baja | F14: =COUNTIF('Backlog por Sprint'!$R$2:$R$71,A14) | G14: =COUNTIFS('Backlog por Sprint'!$R$2:$R$71,A14,'Backlog por Sprint'!$G$2:$G$71,"Hecho") | H14: =COUNTIFS('Backlog por Sprint'!$R$2:$R$71,A14,'Backlog por Sprint'!$G$2:$G$71,"En proceso") | I14: =IF(F14=0,0,G14/F14) | J14: =IF(F14=0,"Sin tareas",IF(G14=F14,"Hecha",IF(G14+H14>0,"En proceso","Por hacer")))
A15: HU-11 | B15: Historia de usuario | C15: Como equipo del proyecto, quiero simular un ciclo CIP completo y controlarlo desde el dashboard, para demostrar y probar el sistema sin sensores. | D15: 1) El simulador recorre todas las etapas con valores realistas. 2) Se inicia y detiene desde un botón del dashboard. 3) Nunca escribe en producción sin indicarlo de forma explícita. | E15: Media | F15: =COUNTIF('Backlog por Sprint'!$R$2:$R$71,A15) | G15: =COUNTIFS('Backlog por Sprint'!$R$2:$R$71,A15,'Backlog por Sprint'!$G$2:$G$71,"Hecho") | H15: =COUNTIFS('Backlog por Sprint'!$R$2:$R$71,A15,'Backlog por Sprint'!$G$2:$G$71,"En proceso") | I15: =IF(F15=0,0,G15/F15) | J15: =IF(F15=0,"Sin tareas",IF(G15=F15,"Hecha",IF(G15+H15>0,"En proceso","Por hacer")))
A16: HU-12 | B16: Historia de usuario | C16: Como operador, quiero que las lecturas de los sensores lleguen solas desde la planta, para no registrar datos a mano. | D16: 1) Un uplink del WQS-LB se decodifica y se guarda en el ciclo en curso. 2) Payloads inválidos o de firmware no soportado se rechazan sin perder el dato crudo. 3) Se prueba con un sensor real de la maqueta. | E16: Alta | F16: =COUNTIF('Backlog por Sprint'!$R$2:$R$71,A16) | G16: =COUNTIFS('Backlog por Sprint'!$R$2:$R$71,A16,'Backlog por Sprint'!$G$2:$G$71,"Hecho") | H16: =COUNTIFS('Backlog por Sprint'!$R$2:$R$71,A16,'Backlog por Sprint'!$G$2:$G$71,"En proceso") | I16: =IF(F16=0,0,G16/F16) | J16: =IF(F16=0,"Sin tareas",IF(G16=F16,"Hecha",IF(G16+H16>0,"En proceso","Por hacer")))
... A22: GE-01 | B22: Gestión del proyecto | C22: Requerimientos, backlog, guion y presentación del MVP al cliente. | D22: Requerimientos validados con el cliente y demo presentada el 04-12-2026. | E22: Alta | F22: =COUNTIF('Backlog por Sprint'!$R$2:$R$71,A22) | G22: =COUNTIFS('Backlog por Sprint'!$R$2:$R$71,A22,'Backlog por Sprint'!$G$2:$G$71,"Hecho") | H22: =COUNTIFS('Backlog por Sprint'!$R$2:$R$71,A22,'Backlog por Sprint'!$G$2:$G$71,"En proceso") | I22: =IF(F22=0,0,G22/F22) | J22: =IF(F22=0,"Sin tareas",IF(G22=F22,"Hecha",IF(G22+H22>0,"En proceso","Por hacer")))
C23: Total de tareas vinculadas | F23: =SUM(F5:F22) | G23: =SUM(G5:G22) | H23: =SUM(H5:H22)
A25: Cómo leer esta hoja:
A26: • HU = historia de usuario: un requisito funcional escrito como 'Como <rol>, quiero <qué>, para <para qué>'.
A27: • HT = habilitador técnico: trabajo necesario que no entrega valor directo a un usuario (infraestructura, datos, calidad).
A28: • GE = gestión del proyecto. Los requisitos no funcionales están en la hoja 'Requisitos no funcionales'.
A29: • El total de tareas vinculadas debe ser 70 (todas las del backlog).

Sheet Requisitos no funcionales
A1: Requisitos no funcionales
A2: BORRADOR propuesto el 19-10-2026. Los valores objetivo de rendimiento y carga están por definir con el equipo y el cliente.
A4: ID | B4: Categoría | C4: Requisito | D4: Cómo se verifica | E4: Estado actual (evidencia)
A5: RNF-01 | B5: Seguridad | C5: Solo usuarios autenticados acceden al sistema y cada rol (admin, operador, visor) ve y modifica solo lo que le corresponde, también a nivel de base de datos. | D5: Tests de reglas de Firestore (functions/reglas) y prueba manual por rol. | E5: Parcial: reglas y tests existen; falta limitar qué campos puede escribir el operador.
A6: RNF-02 | B6: Seguridad | C6: Los secretos (clave del webhook, credenciales) nunca se guardan en el código ni en el repositorio. | D6: Revisión del repositorio y uso de Secret Manager. | E6: Cumple: TTN_WEBHOOK_SECRET en Secret Manager; .secret.local y .env.local fuera de git.
A7: RNF-03 | B7: Seguridad | C7: Solo se aceptan datos de dispositivos registrados y mensajes autenticados. | D7: Caso 'dispositivo desconocido' del simulador TTN y respuesta 401 de /api/ingest sin clave. | E7: Cumple según SPRINT1.md y README de pruebas.
A8: RNF-04 | B8: Confiabilidad | C8: Un mismo mensaje reenviado por la red no genera lecturas ni alertas duplicadas (idempotencia). | D8: Caso 5 de 'npm run sim:ttn'. | E8: Cumple.
A9: RNF-05 | B9: Confiabilidad | C9: Un dato fuera del rango físico de la sonda se rechaza o se marca como saturado o fuera de operación; nunca se muestra como válido. | D9: Tests unitarios de ingest y del decoder. | E9: Cumple.
A10: RNF-06 | B10: Rendimiento | C10: Una lectura aparece en el dashboard pocos segundos después de llegar a la nube (valor objetivo por definir; propuesta: menos de 10 s). | D10: Prueba de rendimiento midiendo desde received_at hasta la pantalla. | E10: Sin medir: no hay pruebas de rendimiento.
A11: RNF-07 | B11: Rendimiento / Escalabilidad | C11: El sistema soporta el flujo continuo de varios sensores durante un ciclo completo sin perder lecturas (carga objetivo por definir). | D11: Prueba de carga del Sprint 7. | E11: Sin medir.
A12: RNF-08 | B12: Disponibilidad | C12: La plataforma está disponible durante los ciclos de limpieza; usa servicios administrados de Google Cloud en southamerica-west1 (Santiago). | D12: Monitoreo de Firebase y prueba de estabilidad de 8 h o más. | E12: Parcial: desplegado en Firebase; falta la prueba de estabilidad.
A13: RNF-09 | B13: Portabilidad | C13: Cualquier integrante puede levantar el entorno de desarrollo en su equipo con un procedimiento documentado y reproducible (Docker). | D13: docker-compose con emuladores, web y scripts; instrucciones en el README. | E13: Falta: no hay Docker; los emuladores fallaron en un equipo por un problema de red de Java.
A14: RNF-10 | B14: Usabilidad | C14: Un dato estimado se distingue siempre de uno medido (borde, color y prefijo '≈'), para no inducir a error al operador. | D14: Revisión del dashboard. | E14: Cumple en los indicadores del ciclo.
A15: RNF-11 | B15: Mantenibilidad | C15: El código tiene pruebas automatizadas y ningún script toca producción sin flags explícitos. | D15: npm test en functions y web (291 tests al 18-10-2026); guardarraíles en scripts/entorno.js. | E15: Cumple.

Sheet Backlog por Sprint
A1: Sprint | B1: Categoría | C1: Tarea / Historia de usuario | D1: Responsable sugerido | E1: Estimación (días) | F1: Dependencias | G1: Estado | H1: Observaciones | I1: Origen | J1: Inicio plan | K1: Fin plan (compromiso) | L1: Término real (evidencia) | M1: Días hábiles esperados | N1: Días hábiles ejecutados | O1: Atraso (días corridos) | P1: Atraso (semanas) | Q1: Situación | R1: Historia (ID)
A2: Sprint 1 | B2: Gestión de proyecto | C2: Levantar requerimientos detallados con el cliente y definir criterios de aceptación del MVP | D2: Felipe | E2: 3 | F2: - | G2: Hecho | I2: Plan original | J2: =IF($I2="Plan original",INDEX('Roadmap Sprints'!$B$2:$B$9,MATCH(IF($A2="Cierre","Semana de cierre",$A2),'Roadmap Sprints'!$A$2:$A$9,0)),"") | K2: =IF($I2="Plan original",INDEX('Roadmap Sprints'!$C$2:$C$9,MATCH(IF($A2="Cierre","Semana de cierre",$A2),'Roadmap Sprints'!$A$2:$A$9,0)),"") | M2: =IF(J2="","",NETWORKDAYS(J2,K2)) | N2: =IF(J2="","",IF(L2<>"",IF(L2<J2,0,NETWORKDAYS(J2,L2)),IF(G2="Hecho","",IF(Avance!$B$2<J2,0,NETWORKDAYS(J2,Avance!$B$2))))) | O2: =IF(J2="","n/a",IF(L2<>"",L2-K2,IF(G2="Hecho","s/d",MAX(0,Avance!$B$2-K2)))) | P2: =IF(ISNUMBER(O2),ROUND(O2/7,1),O2) | Q2: =IF(J2="","No planificada",IF(G2="Hecho",IF(L2="","Hecha (sin fecha)",IF(L2>K2,"Hecha con atraso","Hecha a tiempo")),IF(Avance!$B$2>K2,"Pendiente atrasada","Pendiente en plazo"))) | R2: GE-01
A3: Sprint 1 | B3: Gestión de proyecto | C3: Armar backlog priorizado y tablero ágil (Jira/Trello/Linear) | D3: Tamara | E3: 2 | F3: - | G3: Hecho | I3: Plan original | J3: =IF($I3="Plan original",INDEX('Roadmap Sprints'!$B$2:$B$9,MATCH(IF($A3="Cierre","Semana de cierre",$A3),'Roadmap Sprints'!$A$2:$A$9,0)),"") | K3: =IF($I3="Plan original",INDEX('Roadmap Sprints'!$C$2:$C$9,MATCH(IF($A3="Cierre","Semana de cierre",$A3),'Roadmap Sprints'!$A$2:$A$9,0)),"") | M3: =IF(J3="","",NETWORKDAYS(J3,K3)) | N3: =IF(J3="","",IF(L3<>"",IF(L3<J3,0,NETWORKDAYS(J3,L3)),IF(G3="Hecho","",IF(Avance!$B$2<J3,0,NETWORKDAYS(J3,Avance!$B$2))))) | O3: =IF(J3="","n/a",IF(L3<>"",L3-K3,IF(G3="Hecho","s/d",MAX(0,Avance!$B$2-K3)))) | P3: =IF(ISNUMBER(O3),ROUND(O3/7,1),O3) | Q3: =IF(J3="","No planificada",IF(G3="Hecho",IF(L3="","Hecha (sin fecha)",IF(L3>K3,"Hecha con atraso","Hecha a tiempo")),IF(Avance!$B$2>K3,"Pendiente atrasada","Pendiente en plazo"))) | R3: GE-01
A4: Sprint 1 | B4: Hardware / Sensores | C4: Finalizar cotización de sensores de temperatura, pH, conductividad y caudal/consumo | D4: Felipe | E4: 5 | F4: - | G4: Hecho | H4: Cotización y orden de compra en Gestion Sensores/ (commit d758be2, 07-oct-2026). | I4: Plan original | J4: =IF($I4="Plan original",INDEX('Roadmap Sprints'!$B$2:$B$9,MATCH(IF($A4="Cierre","Semana de cierre",$A4),'Roadmap Sprints'!$A$2:$A$9,0)),"") | K4: =IF($I4="Plan original",INDEX('Roadmap Sprints'!$C$2:$C$9,MATCH(IF($A4="Cierre","Semana de cierre",$A4),'Roadmap Sprints'!$A$2:$A$9,0)),"") | L4: 46302 | M4: =IF(J4="","",NETWORKDAYS(J4,K4)) | N4: =IF(J4="","",IF(L4<>"",IF(L4<J4,0,NETWORKDAYS(J4,L4)),IF(G4="Hecho","",IF(Avance!$B$2<J4,0,NETWORKDAYS(J4,Avance!$B$2))))) | O4: =IF(J4="","n/a",IF(L4<>"",L4-K4,IF(G4="Hecho","s/d",MAX(0,Avance!$B$2-K4)))) | P4: =IF(ISNUMBER(O4),ROUND(O4/7,1),O4) | Q4: =IF(J4="","No planificada",IF(G4="Hecho",IF(L4="","Hecha (sin fecha)",IF(L4>K4,"Hecha con atraso","Hecha a tiempo")),IF(Avance!$B$2>K4,"Pendiente atrasada","Pendiente en plazo"))) | R4: HT-03
A5: Sprint 1 | B5: Backend / Firebase | C5: Crear proyecto en Firebase/GCP y definir estructura (Auth, Firestore, Functions, Hosting) | D5: Humberto y cristian | E5: 3 | F5: - | G5: Hecho | H5: Proyecto stormcip-972bd en producción; Functions, reglas e índices desplegados (SPRINT3.md §2). | I5: Plan original | J5: =IF($I5="Plan original",INDEX('Roadmap Sprints'!$B$2:$B$9,MATCH(IF($A5="Cierre","Semana de cierre",$A5),'Roadmap Sprints'!$A$2:$A$9,0)),"") | K5: =IF($I5="Plan original",INDEX('Roadmap Sprints'!$C$2:$C$9,MATCH(IF($A5="Cierre","Semana de cierre",$A5),'Roadmap Sprints'!$A$2:$A$9,0)),"") | L5: 46286 | M5: =IF(J5="","",NETWORKDAYS(J5,K5)) | N5: =IF(J5="","",IF(L5<>"",IF(L5<J5,0,NETWORKDAYS(J5,L5)),IF(G5="Hecho","",IF(Avance!$B$2<J5,0,NETWORKDAYS(J5,Avance!$B$2))))) | O5: =IF(J5="","n/a",IF(L5<>"",L5-K5,IF(G5="Hecho","s/d",MAX(0,Avance!$B$2-K5)))) | P5: =IF(ISNUMBER(O5),ROUND(O5/7,1),O5) | Q5: =IF(J5="","No planificada",IF(G5="Hecho",IF(L5="","Hecha (sin fecha)",IF(L5>K5,"Hecha con atraso","Hecha a tiempo")),IF(Avance!$B$2>K5,"Pendiente atrasada","Pendiente en plazo"))) | R5: HT-01
A6: Sprint 1 | B6: Backend / Firebase | C6: Diseñar modelo de datos para lecturas de sensores en Firestore/Realtime DB | D6: Humberto y cristian | E6: 3 | F6: Proyecto Firebase creado | G6: Hecho | H6: Modelo v2 documentado en Base de datos/modelo-datos-sensores.md (el manual de sensores ya se recibió). | I6: Plan original | J6: =IF($I6="Plan original",INDEX('Roadmap Sprints'!$B$2:$B$9,MATCH(IF($A6="Cierre","Semana de cierre",$A6),'Roadmap Sprints'!$A$2:$A$9,0)),"") | K6: =IF($I6="Plan original",INDEX('Roadmap Sprints'!$C$2:$C$9,MATCH(IF($A6="Cierre","Semana de cierre",$A6),'Roadmap Sprints'!$A$2:$A$9,0)),"") | L6: 46290 | M6: =IF(J6="","",NETWORKDAYS(J6,K6)) | N6: =IF(J6="","",IF(L6<>"",IF(L6<J6,0,NETWORKDAYS(J6,L6)),IF(G6="Hecho","",IF(Avance!$B$2<J6,0,NETWORKDAYS(J6,Avance!$B$2))))) | O6: =IF(J6="","n/a",IF(L6<>"",L6-K6,IF(G6="Hecho","s/d",MAX(0,Avance!$B$2-K6)))) | P6: =IF(ISNUMBER(O6),ROUND(O6/7,1),O6) | Q6: =IF(J6="","No planificada",IF(G6="Hecho",IF(L6="","Hecha (sin fecha)",IF(L6>K6,"Hecha con atraso","Hecha a tiempo")),IF(Avance!$B$2>K6,"Pendiente atrasada","Pendiente en plazo"))) | R6: HT-02
A7: Sprint 1 | B7: Análisis Predictivo | C7: Diseñar el enfoque de simulación de datos (variables, rangos y patrones física-informados de un ciclo CIP) para poder entrenar los modelos de ML sin esperar datos reales | D7: Dev Backend | E7: 3 | F7: - | G7: Por hacer | H7: Esto más adelante. Existe un simulador CIP para la demo (functions/src/simulacion/modeloCip.ts), pero no el diseño de datos para ML. Se retoma tras la revisión de manuales (oct-2026). | I7: Plan original | J7: =IF($I7="Plan original",INDEX('Roadmap Sprints'!$B$2:$B$9,MATCH(IF($A7="Cierre","Semana de cierre",$A7),'Roadmap Sprints'!$A$2:$A$9,0)),"") | K7: =IF($I7="Plan original",INDEX('Roadmap Sprints'!$C$2:$C$9,MATCH(IF($A7="Cierre","Semana de cierre",$A7),'Roadmap Sprints'!$A$2:$A$9,0)),"") | M7: =IF(J7="","",NETWORKDAYS(J7,K7)) | N7: =IF(J7="","",IF(L7<>"",IF(L7<J7,0,NETWORKDAYS(J7,L7)),IF(G7="Hecho","",IF(Avance!$B$2<J7,0,NETWORKDAYS(J7,Avance!$B$2))))) | O7: =IF(J7="","n/a",IF(L7<>"",L7-K7,IF(G7="Hecho","s/d",MAX(0,Avance!$B$2-K7)))) | P7: =IF(ISNUMBER(O7),ROUND(O7/7,1),O7) | Q7: =IF(J7="","No planificada",IF(G7="Hecho",IF(L7="","Hecha (sin fecha)",IF(L7>K7,"Hecha con atraso","Hecha a tiempo")),IF(Avance!$B$2>K7,"Pendiente atrasada","Pendiente en plazo"))) | R7: HU-07
A8: Sprint 2 | B8: Hardware / Sensores | C8: Emitir orden de compra de sensores y gateway/microcontrolador (ej. ESP32) | D8: Felipe | E8: 3 | F8: Cotización aprobada | G8: Hecho | H8: OC en Gestion Sensores/OrdenDeCompraSensores.pdf. Pendiente confirmar recepción e instalación de los sensores. | I8: Plan original | J8: =IF($I8="Plan original",INDEX('Roadmap Sprints'!$B$2:$B$9,MATCH(IF($A8="Cierre","Semana de cierre",$A8),'Roadmap Sprints'!$A$2:$A$9,0)),"") | K8: =IF($I8="Plan original",INDEX('Roadmap Sprints'!$C$2:$C$9,MATCH(IF($A8="Cierre","Semana de cierre",$A8),'Roadmap Sprints'!$A$2:$A$9,0)),"") | L8: 46302 | M8: =IF(J8="","",NETWORKDAYS(J8,K8)) | N8: =IF(J8="","",IF(L8<>"",IF(L8<J8,0,NETWORKDAYS(J8,L8)),IF(G8="Hecho","",IF(Avance!$B$2<J8,0,NETWORKDAYS(J8,Avance!$B$2))))) | O8: =IF(J8="","n/a",IF(L8<>"",L8-K8,IF(G8="Hecho","s/d",MAX(0,Avance!$B$2-K8)))) | P8: =IF(ISNUMBER(O8),ROUND(O8/7,1),O8) | Q8: =IF(J8="","No planificada",IF(G8="Hecho",IF(L8="","Hecha (sin fecha)",IF(L8>K8,"Hecha con atraso","Hecha a tiempo")),IF(Avance!$B$2>K8,"Pendiente atrasada","Pendiente en plazo"))) | R8: HT-03
A9: Sprint 2 | B9: Auth / Frontend | C9: Implementar Firebase Authentication (login cliente / interno) | D9: Humberto | E9: 5 | F9: Proyecto Firebase creado | G9: Hecho | H9: Login con roles admin / operador / visor (custom claims). | I9: Plan original | J9: =IF($I9="Plan original",INDEX('Roadmap Sprints'!$B$2:$B$9,MATCH(IF($A9="Cierre","Semana de cierre",$A9),'Roadmap Sprints'!$A$2:$A$9,0)),"") | K9: =IF($I9="Plan original",INDEX('Roadmap Sprints'!$C$2:$C$9,MATCH(IF($A9="Cierre","Semana de cierre",$A9),'Roadmap Sprints'!$A$2:$A$9,0)),"") | L9: 46286 | M9: =IF(J9="","",NETWORKDAYS(J9,K9)) | N9: =IF(J9="","",IF(L9<>"",IF(L9<J9,0,NETWORKDAYS(J9,L9)),IF(G9="Hecho","",IF(Avance!$B$2<J9,0,NETWORKDAYS(J9,Avance!$B$2))))) | O9: =IF(J9="","n/a",IF(L9<>"",L9-K9,IF(G9="Hecho","s/d",MAX(0,Avance!$B$2-K9)))) | P9: =IF(ISNUMBER(O9),ROUND(O9/7,1),O9) | Q9: =IF(J9="","No planificada",IF(G9="Hecho",IF(L9="","Hecha (sin fecha)",IF(L9>K9,"Hecha con atraso","Hecha a tiempo")),IF(Avance!$B$2>K9,"Pendiente atrasada","Pendiente en plazo"))) | R9: HU-08
A10: Sprint 2 | B10: Frontend / Dashboard | C10: Scaffolding de la app web (framework, rutas, layout base, conexión a Firebase) | D10: Humberto | E10: 5 | F10: Proyecto Firebase creado | G10: Hecho | H10: App Next.js en Aplicación/stormcip/web. | I10: Plan original | J10: =IF($I10="Plan original",INDEX('Roadmap Sprints'!$B$2:$B$9,MATCH(IF($A10="Cierre","Semana de cierre",$A10),'Roadmap Sprints'!$A$2:$A$9,0)),"") | K10: =IF($I10="Plan original",INDEX('Roadmap Sprints'!$C$2:$C$9,MATCH(IF($A10="Cierre","Semana de cierre",$A10),'Roadmap Sprints'!$A$2:$A$9,0)),"") | L10: 46296 | M10: =IF(J10="","",NETWORKDAYS(J10,K10)) | N10: =IF(J10="","",IF(L10<>"",IF(L10<J10,0,NETWORKDAYS(J10,L10)),IF(G10="Hecho","",IF(Avance!$B$2<J10,0,NETWORKDAYS(J10,Avance!$B$2))))) | O10: =IF(J10="","n/a",IF(L10<>"",L10-K10,IF(G10="Hecho","s/d",MAX(0,Avance!$B$2-K10)))) | P10: =IF(ISNUMBER(O10),ROUND(O10/7,1),O10) | Q10: =IF(J10="","No planificada",IF(G10="Hecho",IF(L10="","Hecha (sin fecha)",IF(L10>K10,"Hecha con atraso","Hecha a tiempo")),IF(Avance!$B$2>K10,"Pendiente atrasada","Pendiente en plazo"))) | R10: HU-01
A11: Sprint 2 | B11: Backend / Firebase | C11: Función HTTP/Callable para recibir datos simulados de sensores | D11: Humberto y cristian | E11: 3 | F11: Modelo de datos definido | G11: Hecho | H11: ingestLectura (POST /api/ingest) y simuladores en scripts/. | I11: Plan original | J11: =IF($I11="Plan original",INDEX('Roadmap Sprints'!$B$2:$B$9,MATCH(IF($A11="Cierre","Semana de cierre",$A11),'Roadmap Sprints'!$A$2:$A$9,0)),"") | K11: =IF($I11="Plan original",INDEX('Roadmap Sprints'!$C$2:$C$9,MATCH(IF($A11="Cierre","Semana de cierre",$A11),'Roadmap Sprints'!$A$2:$A$9,0)),"") | L11: 46286 | M11: =IF(J11="","",NETWORKDAYS(J11,K11)) | N11: =IF(J11="","",IF(L11<>"",IF(L11<J11,0,NETWORKDAYS(J11,L11)),IF(G11="Hecho","",IF(Avance!$B$2<J11,0,NETWORKDAYS(J11,Avance!$B$2))))) | O11: =IF(J11="","n/a",IF(L11<>"",L11-K11,IF(G11="Hecho","s/d",MAX(0,Avance!$B$2-K11)))) | P11: =IF(ISNUMBER(O11),ROUND(O11/7,1),O11) | Q11: =IF(J11="","No planificada",IF(G11="Hecho",IF(L11="","Hecha (sin fecha)",IF(L11>K11,"Hecha con atraso","Hecha a tiempo")),IF(Avance!$B$2>K11,"Pendiente atrasada","Pendiente en plazo"))) | R11: HU-12
A12: Sprint 2 | B12: Análisis Predictivo | C12: Generar el dataset histórico simulado (script Python) con los patrones definidos en Sprint 1 | D12: Dev Backend | E12: 3 | F12: Diseño de la simulación | G12: Por hacer | H12: esto mas adelante | I12: Plan original | J12: =IF($I12="Plan original",INDEX('Roadmap Sprints'!$B$2:$B$9,MATCH(IF($A12="Cierre","Semana de cierre",$A12),'Roadmap Sprints'!$A$2:$A$9,0)),"") | K12: =IF($I12="Plan original",INDEX('Roadmap Sprints'!$C$2:$C$9,MATCH(IF($A12="Cierre","Semana de cierre",$A12),'Roadmap Sprints'!$A$2:$A$9,0)),"") | M12: =IF(J12="","",NETWORKDAYS(J12,K12)) | N12: =IF(J12="","",IF(L12<>"",IF(L12<J12,0,NETWORKDAYS(J12,L12)),IF(G12="Hecho","",IF(Avance!$B$2<J12,0,NETWORKDAYS(J12,Avance!$B$2))))) | O12: =IF(J12="","n/a",IF(L12<>"",L12-K12,IF(G12="Hecho","s/d",MAX(0,Avance!$B$2-K12)))) | P12: =IF(ISNUMBER(O12),ROUND(O12/7,1),O12) | Q12: =IF(J12="","No planificada",IF(G12="Hecho",IF(L12="","Hecha (sin fecha)",IF(L12>K12,"Hecha con atraso","Hecha a tiempo")),IF(Avance!$B$2>K12,"Pendiente atrasada","Pendiente en plazo"))) | R12: HU-07
A13: Sprint 2 | B13: Análisis Predictivo | C13: Entrenar la primera versión de los modelos de ML clásico (regresión / ARIMA-Prophet) con el dataset simulado | D13: Dev Backend | E13: 4 | F13: Dataset simulado generado | G13: Por hacer | H13: esto mas adelante | I13: Plan original | J13: =IF($I13="Plan original",INDEX('Roadmap Sprints'!$B$2:$B$9,MATCH(IF($A13="Cierre","Semana de cierre",$A13),'Roadmap Sprints'!$A$2:$A$9,0)),"") | K13: =IF($I13="Plan original",INDEX('Roadmap Sprints'!$C$2:$C$9,MATCH(IF($A13="Cierre","Semana de cierre",$A13),'Roadmap Sprints'!$A$2:$A$9,0)),"") | M13: =IF(J13="","",NETWORKDAYS(J13,K13)) | N13: =IF(J13="","",IF(L13<>"",IF(L13<J13,0,NETWORKDAYS(J13,L13)),IF(G13="Hecho","",IF(Avance!$B$2<J13,0,NETWORKDAYS(J13,Avance!$B$2))))) | O13: =IF(J13="","n/a",IF(L13<>"",L13-K13,IF(G13="Hecho","s/d",MAX(0,Avance!$B$2-K13)))) | P13: =IF(ISNUMBER(O13),ROUND(O13/7,1),O13) | Q13: =IF(J13="","No planificada",IF(G13="Hecho",IF(L13="","Hecha (sin fecha)",IF(L13>K13,"Hecha con atraso","Hecha a tiempo")),IF(Avance!$B$2>K13,"Pendiente atrasada","Pendiente en plazo"))) | R13: HU-07
A14: Sprint 3 | B14: Hardware / Sensores | C14: Armado estructural de la maqueta (bomba, cañerías, estanques de prueba) | D14: Técnico | E14: 21 | F14: Sensores recibidos | G14: En proceso | H14: Esto es en paralelo. El técnico ya armó el modelo del flujo en una maqueta a escala reducida (18-oct-2026); faltan los sensores. | I14: Plan original | J14: =IF($I14="Plan original",INDEX('Roadmap Sprints'!$B$2:$B$9,MATCH(IF($A14="Cierre","Semana de cierre",$A14),'Roadmap Sprints'!$A$2:$A$9,0)),"") | K14: =IF($I14="Plan original",INDEX('Roadmap Sprints'!$C$2:$C$9,MATCH(IF($A14="Cierre","Semana de cierre",$A14),'Roadmap Sprints'!$A$2:$A$9,0)),"") | M14: =IF(J14="","",NETWORKDAYS(J14,K14)) | N14: =IF(J14="","",IF(L14<>"",IF(L14<J14,0,NETWORKDAYS(J14,L14)),IF(G14="Hecho","",IF(Avance!$B$2<J14,0,NETWORKDAYS(J14,Avance!$B$2))))) | O14: =IF(J14="","n/a",IF(L14<>"",L14-K14,IF(G14="Hecho","s/d",MAX(0,Avance!$B$2-K14)))) | P14: =IF(ISNUMBER(O14),ROUND(O14/7,1),O14) | Q14: =IF(J14="","No planificada",IF(G14="Hecho",IF(L14="","Hecha (sin fecha)",IF(L14>K14,"Hecha con atraso","Hecha a tiempo")),IF(Avance!$B$2>K14,"Pendiente atrasada","Pendiente en plazo"))) | R14: HT-03
A15: Sprint 3 | B15: Hardware / Sensores | C15: Montaje y cableado de sensores en la maqueta | D15: Técnico | E15: 21 | F15: Armado estructural | G15: Por hacer | H15: Esto es en paralelo. Los sensores aún no están instalados en la maqueta (18-oct-2026). | I15: Plan original | J15: =IF($I15="Plan original",INDEX('Roadmap Sprints'!$B$2:$B$9,MATCH(IF($A15="Cierre","Semana de cierre",$A15),'Roadmap Sprints'!$A$2:$A$9,0)),"") | K15: =IF($I15="Plan original",INDEX('Roadmap Sprints'!$C$2:$C$9,MATCH(IF($A15="Cierre","Semana de cierre",$A15),'Roadmap Sprints'!$A$2:$A$9,0)),"") | M15: =IF(J15="","",NETWORKDAYS(J15,K15)) | N15: =IF(J15="","",IF(L15<>"",IF(L15<J15,0,NETWORKDAYS(J15,L15)),IF(G15="Hecho","",IF(Avance!$B$2<J15,0,NETWORKDAYS(J15,Avance!$B$2))))) | O15: =IF(J15="","n/a",IF(L15<>"",L15-K15,IF(G15="Hecho","s/d",MAX(0,Avance!$B$2-K15)))) | P15: =IF(ISNUMBER(O15),ROUND(O15/7,1),O15) | Q15: =IF(J15="","No planificada",IF(G15="Hecho",IF(L15="","Hecha (sin fecha)",IF(L15>K15,"Hecha con atraso","Hecha a tiempo")),IF(Avance!$B$2>K15,"Pendiente atrasada","Pendiente en plazo"))) | R15: HT-03
A16: Sprint 3 | B16: Backend / Firebase | C16: Cloud Function de ingesta de datos reales del gateway → Firestore/Realtime DB | D16: Humberto | E16: 5 | F16: Función con datos simulados | G16: Hecho | H16: Implementada por Humberto (en el plan figuraba Tamara). ttnUplink desplegada; falta probarla con el sensor real. | I16: Plan original | J16: =IF($I16="Plan original",INDEX('Roadmap Sprints'!$B$2:$B$9,MATCH(IF($A16="Cierre","Semana de cierre",$A16),'Roadmap Sprints'!$A$2:$A$9,0)),"") | K16: =IF($I16="Plan original",INDEX('Roadmap Sprints'!$C$2:$C$9,MATCH(IF($A16="Cierre","Semana de cierre",$A16),'Roadmap Sprints'!$A$2:$A$9,0)),"") | L16: 46291 | M16: =IF(J16="","",NETWORKDAYS(J16,K16)) | N16: =IF(J16="","",IF(L16<>"",IF(L16<J16,0,NETWORKDAYS(J16,L16)),IF(G16="Hecho","",IF(Avance!$B$2<J16,0,NETWORKDAYS(J16,Avance!$B$2))))) | O16: =IF(J16="","n/a",IF(L16<>"",L16-K16,IF(G16="Hecho","s/d",MAX(0,Avance!$B$2-K16)))) | P16: =IF(ISNUMBER(O16),ROUND(O16/7,1),O16) | Q16: =IF(J16="","No planificada",IF(G16="Hecho",IF(L16="","Hecha (sin fecha)",IF(L16>K16,"Hecha con atraso","Hecha a tiempo")),IF(Avance!$B$2>K16,"Pendiente atrasada","Pendiente en plazo"))) | R16: HU-12
A17: Sprint 3 | B17: Frontend / Dashboard | C17: Esqueleto de dashboard con gráficos en tiempo real (librería de charts) | D17: Cristian | E17: 5 | F17: Scaffolding app web | G17: Hecho | H17: Dashboard desplegado en https://stormcip-972bd.web.app (SPRINT3.md). | I17: Plan original | J17: =IF($I17="Plan original",INDEX('Roadmap Sprints'!$B$2:$B$9,MATCH(IF($A17="Cierre","Semana de cierre",$A17),'Roadmap Sprints'!$A$2:$A$9,0)),"") | K17: =IF($I17="Plan original",INDEX('Roadmap Sprints'!$C$2:$C$9,MATCH(IF($A17="Cierre","Semana de cierre",$A17),'Roadmap Sprints'!$A$2:$A$9,0)),"") | L17: 46296 | M17: =IF(J17="","",NETWORKDAYS(J17,K17)) | N17: =IF(J17="","",IF(L17<>"",IF(L17<J17,0,NETWORKDAYS(J17,L17)),IF(G17="Hecho","",IF(Avance!$B$2<J17,0,NETWORKDAYS(J17,Avance!$B$2))))) | O17: =IF(J17="","n/a",IF(L17<>"",L17-K17,IF(G17="Hecho","s/d",MAX(0,Avance!$B$2-K17)))) | P17: =IF(ISNUMBER(O17),ROUND(O17/7,1),O17) | Q17: =IF(J17="","No planificada",IF(G17="Hecho",IF(L17="","Hecha (sin fecha)",IF(L17>K17,"Hecha con atraso","Hecha a tiempo")),IF(Avance!$B$2>K17,"Pendiente atrasada","Pendiente en plazo"))) | R17: HU-01
A18: Sprint 3 | B18: Análisis Predictivo | C18: Integrar el modelo ML entrenado al backend (Cloud Function que sirva predicciones) | D18: Dev Backend | E18: 4 | F18: Modelo entrenado con datos simulados | G18: Por hacer | H18: Esto más adelante. No entregado en Sprint 3 (SPRINT3.md §3); depende de entrenar el primer modelo. | I18: Plan original | J18: =IF($I18="Plan original",INDEX('Roadmap Sprints'!$B$2:$B$9,MATCH(IF($A18="Cierre","Semana de cierre",$A18),'Roadmap Sprints'!$A$2:$A$9,0)),"") | K18: =IF($I18="Plan original",INDEX('Roadmap Sprints'!$C$2:$C$9,MATCH(IF($A18="Cierre","Semana de cierre",$A18),'Roadmap Sprints'!$A$2:$A$9,0)),"") | M18: =IF(J18="","",NETWORKDAYS(J18,K18)) | N18: =IF(J18="","",IF(L18<>"",IF(L18<J18,0,NETWORKDAYS(J18,L18)),IF(G18="Hecho","",IF(Avance!$B$2<J18,0,NETWORKDAYS(J18,Avance!$B$2))))) | O18: =IF(J18="","n/a",IF(L18<>"",L18-K18,IF(G18="Hecho","s/d",MAX(0,Avance!$B$2-K18)))) | P18: =IF(ISNUMBER(O18),ROUND(O18/7,1),O18) | Q18: =IF(J18="","No planificada",IF(G18="Hecho",IF(L18="","Hecha (sin fecha)",IF(L18>K18,"Hecha con atraso","Hecha a tiempo")),IF(Avance!$B$2>K18,"Pendiente atrasada","Pendiente en plazo"))) | R18: HU-07
A19: Sprint 3 | B19: Hardware / Sensores | C19: Reunir información técnica de los sensores LoRaWAN (WQS-LB) en la carpeta de evidencias | D19: Felipe | E19: 1 | F19: - | G19: Hecho | H19: Commits b1debe1 y 0c1f9b2 (21-sep). Datasheet, certificaciones y firmware. [Estimación retroactiva] | I19: Agregada (no planificada) | J19: =IF($I19="Plan original",INDEX('Roadmap Sprints'!$B$2:$B$9,MATCH(IF($A19="Cierre","Semana de cierre",$A19),'Roadmap Sprints'!$A$2:$A$9,0)),"") | K19: =IF($I19="Plan original",INDEX('Roadmap Sprints'!$C$2:$C$9,MATCH(IF($A19="Cierre","Semana de cierre",$A19),'Roadmap Sprints'!$A$2:$A$9,0)),"") | L19: 46286 | M19: =IF(J19="","",NETWORKDAYS(J19,K19)) | N19: =IF(J19="","",IF(L19<>"",IF(L19<J19,0,NETWORKDAYS(J19,L19)),IF(G19="Hecho","",IF(Avance!$B$2<J19,0,NETWORKDAYS(J19,Avance!$B$2))))) | O19: =IF(J19="","n/a",IF(L19<>"",L19-K19,IF(G19="Hecho","s/d",MAX(0,Avance!$B$2-K19)))) | P19: =IF(ISNUMBER(O19),ROUND(O19/7,1),O19) | Q19: =IF(J19="","No planificada",IF(G19="Hecho",IF(L19="","Hecha (sin fecha)",IF(L19>K19,"Hecha con atraso","Hecha a tiempo")),IF(Avance!$B$2>K19,"Pendiente atrasada","Pendiente en plazo"))) | R19: HT-03
A20: Sprint 3 | B20: Backend / Firebase | C20: Diseño de datos de las sondas WQS y validación de rango físico | D20: Humberto | E20: 2 | F20: Información técnica de sensores | G20: Hecho | H20: Commit 8d55ccc (25-sep). Base de datos/modelo-datos-sensores.md. [Estimación retroactiva] | I20: Agregada (no planificada) | J20: =IF($I20="Plan original",INDEX('Roadmap Sprints'!$B$2:$B$9,MATCH(IF($A20="Cierre","Semana de cierre",$A20),'Roadmap Sprints'!$A$2:$A$9,0)),"") | K20: =IF($I20="Plan original",INDEX('Roadmap Sprints'!$C$2:$C$9,MATCH(IF($A20="Cierre","Semana de cierre",$A20),'Roadmap Sprints'!$A$2:$A$9,0)),"") | L20: 46290 | M20: =IF(J20="","",NETWORKDAYS(J20,K20)) | N20: =IF(J20="","",IF(L20<>"",IF(L20<J20,0,NETWORKDAYS(J20,L20)),IF(G20="Hecho","",IF(Avance!$B$2<J20,0,NETWORKDAYS(J20,Avance!$B$2))))) | O20: =IF(J20="","n/a",IF(L20<>"",L20-K20,IF(G20="Hecho","s/d",MAX(0,Avance!$B$2-K20)))) | P20: =IF(ISNUMBER(O20),ROUND(O20/7,1),O20) | Q20: =IF(J20="","No planificada",IF(G20="Hecho",IF(L20="","Hecha (sin fecha)",IF(L20>K20,"Hecha con atraso","Hecha a tiempo")),IF(Avance!$B$2>K20,"Pendiente atrasada","Pendiente en plazo"))) | R20: HT-02
A21: Sprint 3 | B21: Backend / Firebase | C21: Documentar arquitectura LoRaWAN -> The Things Stack -> backend e implementar el adaptador LoRaWAN | D21: Humberto | E21: 3 | F21: Diseño de datos de sondas | G21: Hecho | H21: Commits 44b3b02 y b22a97b (25/26-sep). functions/src/lorawanAdapter.ts. [Estimación retroactiva] | I21: Agregada (no planificada) | J21: =IF($I21="Plan original",INDEX('Roadmap Sprints'!$B$2:$B$9,MATCH(IF($A21="Cierre","Semana de cierre",$A21),'Roadmap Sprints'!$A$2:$A$9,0)),"") | K21: =IF($I21="Plan original",INDEX('Roadmap Sprints'!$C$2:$C$9,MATCH(IF($A21="Cierre","Semana de cierre",$A21),'Roadmap Sprints'!$A$2:$A$9,0)),"") | L21: 46291 | M21: =IF(J21="","",NETWORKDAYS(J21,K21)) | N21: =IF(J21="","",IF(L21<>"",IF(L21<J21,0,NETWORKDAYS(J21,L21)),IF(G21="Hecho","",IF(Avance!$B$2<J21,0,NETWORKDAYS(J21,Avance!$B$2))))) | O21: =IF(J21="","n/a",IF(L21<>"",L21-K21,IF(G21="Hecho","s/d",MAX(0,Avance!$B$2-K21)))) | P21: =IF(ISNUMBER(O21),ROUND(O21/7,1),O21) | Q21: =IF(J21="","No planificada",IF(G21="Hecho",IF(L21="","Hecha (sin fecha)",IF(L21>K21,"Hecha con atraso","Hecha a tiempo")),IF(Avance!$B$2>K21,"Pendiente atrasada","Pendiente en plazo"))) | R21: HU-12
A22: Sprint 3 | B22: Backend / Firebase | C22: Decoder propio del WQS-LB por versión de firmware, con validación de largo y tests | D22: Humberto | E22: 4 | F22: Adaptador LoRaWAN | G22: Hecho | H22: Commit cc59b42 (26-sep). wqsDecoder.ts; no se usa el decoder de Dragino (corresponde a firmware 1.1). [Estimación retroactiva] | I22: Agregada (no planificada) | J22: =IF($I22="Plan original",INDEX('Roadmap Sprints'!$B$2:$B$9,MATCH(IF($A22="Cierre","Semana de cierre",$A22),'Roadmap Sprints'!$A$2:$A$9,0)),"") | K22: =IF($I22="Plan original",INDEX('Roadmap Sprints'!$C$2:$C$9,MATCH(IF($A22="Cierre","Semana de cierre",$A22),'Roadmap Sprints'!$A$2:$A$9,0)),"") | L22: 46291 | M22: =IF(J22="","",NETWORKDAYS(J22,K22)) | N22: =IF(J22="","",IF(L22<>"",IF(L22<J22,0,NETWORKDAYS(J22,L22)),IF(G22="Hecho","",IF(Avance!$B$2<J22,0,NETWORKDAYS(J22,Avance!$B$2))))) | O22: =IF(J22="","n/a",IF(L22<>"",L22-K22,IF(G22="Hecho","s/d",MAX(0,Avance!$B$2-K22)))) | P22: =IF(ISNUMBER(O22),ROUND(O22/7,1),O22) | Q22: =IF(J22="","No planificada",IF(G22="Hecho",IF(L22="","Hecha (sin fecha)",IF(L22>K22,"Hecha con atraso","Hecha a tiempo")),IF(Avance!$B$2>K22,"Pendiente atrasada","Pendiente en plazo"))) | R22: HU-12
A23: Sprint 3 | B23: QA / DevOps / Documentación | C23: Documentación para el equipo: CLAUDE.MD y documento explicativo del sistema de sensores | D23: Humberto | E23: 1 | F23: - | G23: Hecho | H23: Commits 9a33f38, 9f36c20 (26-sep). [Estimación retroactiva] | I23: Agregada (no planificada) | J23: =IF($I23="Plan original",INDEX('Roadmap Sprints'!$B$2:$B$9,MATCH(IF($A23="Cierre","Semana de cierre",$A23),'Roadmap Sprints'!$A$2:$A$9,0)),"") | K23: =IF($I23="Plan original",INDEX('Roadmap Sprints'!$C$2:$C$9,MATCH(IF($A23="Cierre","Semana de cierre",$A23),'Roadmap Sprints'!$A$2:$A$9,0)),"") | L23: 46291 | M23: =IF(J23="","",NETWORKDAYS(J23,K23)) | N23: =IF(J23="","",IF(L23<>"",IF(L23<J23,0,NETWORKDAYS(J23,L23)),IF(G23="Hecho","",IF(Avance!$B$2<J23,0,NETWORKDAYS(J23,Avance!$B$2))))) | O23: =IF(J23="","n/a",IF(L23<>"",L23-K23,IF(G23="Hecho","s/d",MAX(0,Avance!$B$2-K23)))) | P23: =IF(ISNUMBER(O23),ROUND(O23/7,1),O23) | Q23: =IF(J23="","No planificada",IF(G23="Hecho",IF(L23="","Hecha (sin fecha)",IF(L23>K23,"Hecha con atraso","Hecha a tiempo")),IF(Avance!$B$2>K23,"Pendiente atrasada","Pendiente en plazo"))) | R23: HT-05
A24: Sprint 3 | B24: QA / DevOps / Documentación | C24: Scripts con PROJECT_ID centralizado y caso de idempotencia en las pruebas | D24: Humberto | E24: 1 | F24: - | G24: Hecho | H24: Commit 84da283 (26-sep). [Estimación retroactiva] | I24: Agregada (no planificada) | J24: =IF($I24="Plan original",INDEX('Roadmap Sprints'!$B$2:$B$9,MATCH(IF($A24="Cierre","Semana de cierre",$A24),'Roadmap Sprints'!$A$2:$A$9,0)),"") | K24: =IF($I24="Plan original",INDEX('Roadmap Sprints'!$C$2:$C$9,MATCH(IF($A24="Cierre","Semana de cierre",$A24),'Roadmap Sprints'!$A$2:$A$9,0)),"") | L24: 46291 | M24: =IF(J24="","",NETWORKDAYS(J24,K24)) | N24: =IF(J24="","",IF(L24<>"",IF(L24<J24,0,NETWORKDAYS(J24,L24)),IF(G24="Hecho","",IF(Avance!$B$2<J24,0,NETWORKDAYS(J24,Avance!$B$2))))) | O24: =IF(J24="","n/a",IF(L24<>"",L24-K24,IF(G24="Hecho","s/d",MAX(0,Avance!$B$2-K24)))) | P24: =IF(ISNUMBER(O24),ROUND(O24/7,1),O24) | Q24: =IF(J24="","No planificada",IF(G24="Hecho",IF(L24="","Hecha (sin fecha)",IF(L24>K24,"Hecha con atraso","Hecha a tiempo")),IF(Avance!$B$2>K24,"Pendiente atrasada","Pendiente en plazo"))) | R24: HT-04
A25: Sprint 3 | B25: Backend / Firebase | C25: Preparar el despliegue a producción: secreto en Secret Manager, guía DESPLIEGUE.md, runtime Node 22 y región de onUserCreated | D25: Humberto | E25: 3 | F25: Proyecto Firebase creado | G25: Hecho | H25: Commits 9978091, 24f42ff, de1ec7b (29/30-sep). [Estimación retroactiva] | I25: Agregada (no planificada) | J25: =IF($I25="Plan original",INDEX('Roadmap Sprints'!$B$2:$B$9,MATCH(IF($A25="Cierre","Semana de cierre",$A25),'Roadmap Sprints'!$A$2:$A$9,0)),"") | K25: =IF($I25="Plan original",INDEX('Roadmap Sprints'!$C$2:$C$9,MATCH(IF($A25="Cierre","Semana de cierre",$A25),'Roadmap Sprints'!$A$2:$A$9,0)),"") | L25: 46295 | M25: =IF(J25="","",NETWORKDAYS(J25,K25)) | N25: =IF(J25="","",IF(L25<>"",IF(L25<J25,0,NETWORKDAYS(J25,L25)),IF(G25="Hecho","",IF(Avance!$B$2<J25,0,NETWORKDAYS(J25,Avance!$B$2))))) | O25: =IF(J25="","n/a",IF(L25<>"",L25-K25,IF(G25="Hecho","s/d",MAX(0,Avance!$B$2-K25)))) | P25: =IF(ISNUMBER(O25),ROUND(O25/7,1),O25) | Q25: =IF(J25="","No planificada",IF(G25="Hecho",IF(L25="","Hecha (sin fecha)",IF(L25>K25,"Hecha con atraso","Hecha a tiempo")),IF(Avance!$B$2>K25,"Pendiente atrasada","Pendiente en plazo"))) | R25: HT-01
A26: Sprint 3 | B26: Backend / Firebase | C26: Trigger de cierre de ciclo que calcula indicadores (tiempo hasta limpio, arrastre químico, pendiente de conductividad, volumen estimado) | D26: Cristian | E26: 4 | F26: Ingesta de datos | G26: Hecho | H26: Commit 831c580 (01-oct). functions/src/ciclos.ts y calculos.ts. [Estimación retroactiva] | I26: Agregada (no planificada) | J26: =IF($I26="Plan original",INDEX('Roadmap Sprints'!$B$2:$B$9,MATCH(IF($A26="Cierre","Semana de cierre",$A26),'Roadmap Sprints'!$A$2:$A$9,0)),"") | K26: =IF($I26="Plan original",INDEX('Roadmap Sprints'!$C$2:$C$9,MATCH(IF($A26="Cierre","Semana de cierre",$A26),'Roadmap Sprints'!$A$2:$A$9,0)),"") | L26: 46296 | M26: =IF(J26="","",NETWORKDAYS(J26,K26)) | N26: =IF(J26="","",IF(L26<>"",IF(L26<J26,0,NETWORKDAYS(J26,L26)),IF(G26="Hecho","",IF(Avance!$B$2<J26,0,NETWORKDAYS(J26,Avance!$B$2))))) | O26: =IF(J26="","n/a",IF(L26<>"",L26-K26,IF(G26="Hecho","s/d",MAX(0,Avance!$B$2-K26)))) | P26: =IF(ISNUMBER(O26),ROUND(O26/7,1),O26) | Q26: =IF(J26="","No planificada",IF(G26="Hecho",IF(L26="","Hecha (sin fecha)",IF(L26>K26,"Hecha con atraso","Hecha a tiempo")),IF(Avance!$B$2>K26,"Pendiente atrasada","Pendiente en plazo"))) | R26: HU-06
A27: Sprint 3 | B27: Frontend / Dashboard | C27: Sección de indicadores del ciclo en el dashboard (medido vs estimado) y regla de grupo de colección para el histórico | D27: Cristian | E27: 2 | F27: Trigger de cierre de ciclo | G27: Hecho | H27: Commits 103fc10, 33094b7 (01-oct). [Estimación retroactiva] | I27: Agregada (no planificada) | J27: =IF($I27="Plan original",INDEX('Roadmap Sprints'!$B$2:$B$9,MATCH(IF($A27="Cierre","Semana de cierre",$A27),'Roadmap Sprints'!$A$2:$A$9,0)),"") | K27: =IF($I27="Plan original",INDEX('Roadmap Sprints'!$C$2:$C$9,MATCH(IF($A27="Cierre","Semana de cierre",$A27),'Roadmap Sprints'!$A$2:$A$9,0)),"") | L27: 46296 | M27: =IF(J27="","",NETWORKDAYS(J27,K27)) | N27: =IF(J27="","",IF(L27<>"",IF(L27<J27,0,NETWORKDAYS(J27,L27)),IF(G27="Hecho","",IF(Avance!$B$2<J27,0,NETWORKDAYS(J27,Avance!$B$2))))) | O27: =IF(J27="","n/a",IF(L27<>"",L27-K27,IF(G27="Hecho","s/d",MAX(0,Avance!$B$2-K27)))) | P27: =IF(ISNUMBER(O27),ROUND(O27/7,1),O27) | Q27: =IF(J27="","No planificada",IF(G27="Hecho",IF(L27="","Hecha (sin fecha)",IF(L27>K27,"Hecha con atraso","Hecha a tiempo")),IF(Avance!$B$2>K27,"Pendiente atrasada","Pendiente en plazo"))) | R27: HU-06
A28: Sprint 3 | B28: Backend / Firebase | C28: Scripts de seed, simulador y cierre de ciclo contra producción (sin credenciales en el código); migración al modelo v2 | D28: Cristian | E28: 2 | F28: Modelo de datos | G28: Hecho | H28: Commits 779388c, 5e85914, 7e2b3d1 (01-oct). [Estimación retroactiva] | I28: Agregada (no planificada) | J28: =IF($I28="Plan original",INDEX('Roadmap Sprints'!$B$2:$B$9,MATCH(IF($A28="Cierre","Semana de cierre",$A28),'Roadmap Sprints'!$A$2:$A$9,0)),"") | K28: =IF($I28="Plan original",INDEX('Roadmap Sprints'!$C$2:$C$9,MATCH(IF($A28="Cierre","Semana de cierre",$A28),'Roadmap Sprints'!$A$2:$A$9,0)),"") | L28: 46296 | M28: =IF(J28="","",NETWORKDAYS(J28,K28)) | N28: =IF(J28="","",IF(L28<>"",IF(L28<J28,0,NETWORKDAYS(J28,L28)),IF(G28="Hecho","",IF(Avance!$B$2<J28,0,NETWORKDAYS(J28,Avance!$B$2))))) | O28: =IF(J28="","n/a",IF(L28<>"",L28-K28,IF(G28="Hecho","s/d",MAX(0,Avance!$B$2-K28)))) | P28: =IF(ISNUMBER(O28),ROUND(O28/7,1),O28) | Q28: =IF(J28="","No planificada",IF(G28="Hecho",IF(L28="","Hecha (sin fecha)",IF(L28>K28,"Hecha con atraso","Hecha a tiempo")),IF(Avance!$B$2>K28,"Pendiente atrasada","Pendiente en plazo"))) | R28: HT-04
A29: Sprint 3 | B29: QA / DevOps / Documentación | C29: Primer despliegue a producción (Hosting con cleanUrls y Functions) y documento de cierre del Sprint 3 | D29: Cristian | E29: 2 | F29: Despliegue preparado | G29: Hecho | H29: Commits b4cf6bf, 0e7e056 (01-oct). https://stormcip-972bd.web.app. [Estimación retroactiva] | I29: Agregada (no planificada) | J29: =IF($I29="Plan original",INDEX('Roadmap Sprints'!$B$2:$B$9,MATCH(IF($A29="Cierre","Semana de cierre",$A29),'Roadmap Sprints'!$A$2:$A$9,0)),"") | K29: =IF($I29="Plan original",INDEX('Roadmap Sprints'!$C$2:$C$9,MATCH(IF($A29="Cierre","Semana de cierre",$A29),'Roadmap Sprints'!$A$2:$A$9,0)),"") | L29: 46296 | M29: =IF(J29="","",NETWORKDAYS(J29,K29)) | N29: =IF(J29="","",IF(L29<>"",IF(L29<J29,0,NETWORKDAYS(J29,L29)),IF(G29="Hecho","",IF(Avance!$B$2<J29,0,NETWORKDAYS(J29,Avance!$B$2))))) | O29: =IF(J29="","n/a",IF(L29<>"",L29-K29,IF(G29="Hecho","s/d",MAX(0,Avance!$B$2-K29)))) | P29: =IF(ISNUMBER(O29),ROUND(O29/7,1),O29) | Q29: =IF(J29="","No planificada",IF(G29="Hecho",IF(L29="","Hecha (sin fecha)",IF(L29>K29,"Hecha con atraso","Hecha a tiempo")),IF(Avance!$B$2>K29,"Pendiente atrasada","Pendiente en plazo"))) | R29: HT-01
A30: Sprint 4 | B30: Hardware / Sensores | C30: Calibración de sensores de temperatura y pH en la maqueta | D30: Técnico | E30: 4 | F30: Sensores montados | G30: Por hacer | I30: Plan original | J30: =IF($I30="Plan original",INDEX('Roadmap Sprints'!$B$2:$B$9,MATCH(IF($A30="Cierre","Semana de cierre",$A30),'Roadmap Sprints'!$A$2:$A$9,0)),"") | K30: =IF($I30="Plan original",INDEX('Roadmap Sprints'!$C$2:$C$9,MATCH(IF($A30="Cierre","Semana de cierre",$A30),'Roadmap Sprints'!$A$2:$A$9,0)),"") | M30: =IF(J30="","",NETWORKDAYS(J30,K30)) | N30: =IF(J30="","",IF(L30<>"",IF(L30<J30,0,NETWORKDAYS(J30,L30)),IF(G30="Hecho","",IF(Avance!$B$2<J30,0,NETWORKDAYS(J30,Avance!$B$2))))) | O30: =IF(J30="","n/a",IF(L30<>"",L30-K30,IF(G30="Hecho","s/d",MAX(0,Avance!$B$2-K30)))) | P30: =IF(ISNUMBER(O30),ROUND(O30/7,1),O30) | Q30: =IF(J30="","No planificada",IF(G30="Hecho",IF(L30="","Hecha (sin fecha)",IF(L30>K30,"Hecha con atraso","Hecha a tiempo")),IF(Avance!$B$2>K30,"Pendiente atrasada","Pendiente en plazo"))) | R30: HT-03
A31: Sprint 4 | B31: Backend / Firebase | C31: Conectar Function de ingesta a datos reales de la maqueta (2 sensores) | D31: Dev Backend | E31: 4 | F31: Maqueta enviando datos | G31: Por hacer | H31: ttnUplink listo y probado con simulador TTN; falta el sensor real y el primer uplink FPort 5 para confirmar firmware. | I31: Plan original | J31: =IF($I31="Plan original",INDEX('Roadmap Sprints'!$B$2:$B$9,MATCH(IF($A31="Cierre","Semana de cierre",$A31),'Roadmap Sprints'!$A$2:$A$9,0)),"") | K31: =IF($I31="Plan original",INDEX('Roadmap Sprints'!$C$2:$C$9,MATCH(IF($A31="Cierre","Semana de cierre",$A31),'Roadmap Sprints'!$A$2:$A$9,0)),"") | M31: =IF(J31="","",NETWORKDAYS(J31,K31)) | N31: =IF(J31="","",IF(L31<>"",IF(L31<J31,0,NETWORKDAYS(J31,L31)),IF(G31="Hecho","",IF(Avance!$B$2<J31,0,NETWORKDAYS(J31,Avance!$B$2))))) | O31: =IF(J31="","n/a",IF(L31<>"",L31-K31,IF(G31="Hecho","s/d",MAX(0,Avance!$B$2-K31)))) | P31: =IF(ISNUMBER(O31),ROUND(O31/7,1),O31) | Q31: =IF(J31="","No planificada",IF(G31="Hecho",IF(L31="","Hecha (sin fecha)",IF(L31>K31,"Hecha con atraso","Hecha a tiempo")),IF(Avance!$B$2>K31,"Pendiente atrasada","Pendiente en plazo"))) | R31: HU-12
A32: Sprint 4 | B32: Frontend / Dashboard | C32: Gráfico en tiempo real de temperatura y pH conectado a Firestore listeners | D32: Cristian | E32: 5 | F32: Esqueleto de dashboard | G32: Hecho | H32: Gráfico de tendencia con listeners de Firestore, funcionando con datos simulados (sim:cip); falta validarlo con sensores reales. | I32: Plan original | J32: =IF($I32="Plan original",INDEX('Roadmap Sprints'!$B$2:$B$9,MATCH(IF($A32="Cierre","Semana de cierre",$A32),'Roadmap Sprints'!$A$2:$A$9,0)),"") | K32: =IF($I32="Plan original",INDEX('Roadmap Sprints'!$C$2:$C$9,MATCH(IF($A32="Cierre","Semana de cierre",$A32),'Roadmap Sprints'!$A$2:$A$9,0)),"") | L32: 46309 | M32: =IF(J32="","",NETWORKDAYS(J32,K32)) | N32: =IF(J32="","",IF(L32<>"",IF(L32<J32,0,NETWORKDAYS(J32,L32)),IF(G32="Hecho","",IF(Avance!$B$2<J32,0,NETWORKDAYS(J32,Avance!$B$2))))) | O32: =IF(J32="","n/a",IF(L32<>"",L32-K32,IF(G32="Hecho","s/d",MAX(0,Avance!$B$2-K32)))) | P32: =IF(ISNUMBER(O32),ROUND(O32/7,1),O32) | Q32: =IF(J32="","No planificada",IF(G32="Hecho",IF(L32="","Hecha (sin fecha)",IF(L32>K32,"Hecha con atraso","Hecha a tiempo")),IF(Avance!$B$2>K32,"Pendiente atrasada","Pendiente en plazo"))) | R32: HU-01
A33: Sprint 4 | B33: Análisis Predictivo | C33: Primer panel de análisis predictivo en el dashboard (proyección/alerta, aún con modelo entrenado solo en datos simulados) | D33: Dev Frontend | E33: 4 | F33: Modelo servido desde el backend | G33: Por hacer | I33: Plan original | J33: =IF($I33="Plan original",INDEX('Roadmap Sprints'!$B$2:$B$9,MATCH(IF($A33="Cierre","Semana de cierre",$A33),'Roadmap Sprints'!$A$2:$A$9,0)),"") | K33: =IF($I33="Plan original",INDEX('Roadmap Sprints'!$C$2:$C$9,MATCH(IF($A33="Cierre","Semana de cierre",$A33),'Roadmap Sprints'!$A$2:$A$9,0)),"") | M33: =IF(J33="","",NETWORKDAYS(J33,K33)) | N33: =IF(J33="","",IF(L33<>"",IF(L33<J33,0,NETWORKDAYS(J33,L33)),IF(G33="Hecho","",IF(Avance!$B$2<J33,0,NETWORKDAYS(J33,Avance!$B$2))))) | O33: =IF(J33="","n/a",IF(L33<>"",L33-K33,IF(G33="Hecho","s/d",MAX(0,Avance!$B$2-K33)))) | P33: =IF(ISNUMBER(O33),ROUND(O33/7,1),O33) | Q33: =IF(J33="","No planificada",IF(G33="Hecho",IF(L33="","Hecha (sin fecha)",IF(L33>K33,"Hecha con atraso","Hecha a tiempo")),IF(Avance!$B$2>K33,"Pendiente atrasada","Pendiente en plazo"))) | R33: HU-07
A34: Sprint 4 | B34: QA / DevOps / Documentación | C34: Demo interna end-to-end (sensor → Function → dashboard → predictivo) | D34: Equipo completo | E34: 1 | F34: Panel predictivo visible | G34: En proceso | H34: End-to-end simulado funcionando (simulador TTN -> ttnUplink -> dashboard, con botón de demo). Falta con sensor real y panel predictivo. | I34: Plan original | J34: =IF($I34="Plan original",INDEX('Roadmap Sprints'!$B$2:$B$9,MATCH(IF($A34="Cierre","Semana de cierre",$A34),'Roadmap Sprints'!$A$2:$A$9,0)),"") | K34: =IF($I34="Plan original",INDEX('Roadmap Sprints'!$C$2:$C$9,MATCH(IF($A34="Cierre","Semana de cierre",$A34),'Roadmap Sprints'!$A$2:$A$9,0)),"") | M34: =IF(J34="","",NETWORKDAYS(J34,K34)) | N34: =IF(J34="","",IF(L34<>"",IF(L34<J34,0,NETWORKDAYS(J34,L34)),IF(G34="Hecho","",IF(Avance!$B$2<J34,0,NETWORKDAYS(J34,Avance!$B$2))))) | O34: =IF(J34="","n/a",IF(L34<>"",L34-K34,IF(G34="Hecho","s/d",MAX(0,Avance!$B$2-K34)))) | P34: =IF(ISNUMBER(O34),ROUND(O34/7,1),O34) | Q34: =IF(J34="","No planificada",IF(G34="Hecho",IF(L34="","Hecha (sin fecha)",IF(L34>K34,"Hecha con atraso","Hecha a tiempo")),IF(Avance!$B$2>K34,"Pendiente atrasada","Pendiente en plazo"))) | R34: HT-04
A35: Sprint 4 | B35: Frontend / Dashboard | C35: Sección de historial de alertas en el dashboard | D35: Humberto | E35: 2 | F35: Dashboard base | G35: Hecho | H35: Commit 1ddb7eb (05-oct). [Estimación retroactiva] | I35: Agregada (no planificada) | J35: =IF($I35="Plan original",INDEX('Roadmap Sprints'!$B$2:$B$9,MATCH(IF($A35="Cierre","Semana de cierre",$A35),'Roadmap Sprints'!$A$2:$A$9,0)),"") | K35: =IF($I35="Plan original",INDEX('Roadmap Sprints'!$C$2:$C$9,MATCH(IF($A35="Cierre","Semana de cierre",$A35),'Roadmap Sprints'!$A$2:$A$9,0)),"") | L35: 46300 | M35: =IF(J35="","",NETWORKDAYS(J35,K35)) | N35: =IF(J35="","",IF(L35<>"",IF(L35<J35,0,NETWORKDAYS(J35,L35)),IF(G35="Hecho","",IF(Avance!$B$2<J35,0,NETWORKDAYS(J35,Avance!$B$2))))) | O35: =IF(J35="","n/a",IF(L35<>"",L35-K35,IF(G35="Hecho","s/d",MAX(0,Avance!$B$2-K35)))) | P35: =IF(ISNUMBER(O35),ROUND(O35/7,1),O35) | Q35: =IF(J35="","No planificada",IF(G35="Hecho",IF(L35="","Hecha (sin fecha)",IF(L35>K35,"Hecha con atraso","Hecha a tiempo")),IF(Avance!$B$2>K35,"Pendiente atrasada","Pendiente en plazo"))) | R35: HU-03
A36: Sprint 4 | B36: Auth / Frontend | C36: Proteger el dashboard por rol (GuardRol) y desacoplar el panel del login | D36: Humberto | E36: 2 | F36: Firebase Authentication | G36: Hecho | H36: Commit 6807633 (06-oct). [Estimación retroactiva] | I36: Agregada (no planificada) | J36: =IF($I36="Plan original",INDEX('Roadmap Sprints'!$B$2:$B$9,MATCH(IF($A36="Cierre","Semana de cierre",$A36),'Roadmap Sprints'!$A$2:$A$9,0)),"") | K36: =IF($I36="Plan original",INDEX('Roadmap Sprints'!$C$2:$C$9,MATCH(IF($A36="Cierre","Semana de cierre",$A36),'Roadmap Sprints'!$A$2:$A$9,0)),"") | L36: 46301 | M36: =IF(J36="","",NETWORKDAYS(J36,K36)) | N36: =IF(J36="","",IF(L36<>"",IF(L36<J36,0,NETWORKDAYS(J36,L36)),IF(G36="Hecho","",IF(Avance!$B$2<J36,0,NETWORKDAYS(J36,Avance!$B$2))))) | O36: =IF(J36="","n/a",IF(L36<>"",L36-K36,IF(G36="Hecho","s/d",MAX(0,Avance!$B$2-K36)))) | P36: =IF(ISNUMBER(O36),ROUND(O36/7,1),O36) | Q36: =IF(J36="","No planificada",IF(G36="Hecho",IF(L36="","Hecha (sin fecha)",IF(L36>K36,"Hecha con atraso","Hecha a tiempo")),IF(Avance!$B$2>K36,"Pendiente atrasada","Pendiente en plazo"))) | R36: HU-08
A37: Sprint 4 | B37: Frontend / Dashboard | C37: Conexión de la base de datos con la web (primeros pasos del front) | D37: Cristian | E37: 2 | F37: Scaffolding app web | G37: Hecho | H37: Commit 6eb4457 (05-oct). [Estimación retroactiva] | I37: Agregada (no planificada) | J37: =IF($I37="Plan original",INDEX('Roadmap Sprints'!$B$2:$B$9,MATCH(IF($A37="Cierre","Semana de cierre",$A37),'Roadmap Sprints'!$A$2:$A$9,0)),"") | K37: =IF($I37="Plan original",INDEX('Roadmap Sprints'!$C$2:$C$9,MATCH(IF($A37="Cierre","Semana de cierre",$A37),'Roadmap Sprints'!$A$2:$A$9,0)),"") | L37: 46300 | M37: =IF(J37="","",NETWORKDAYS(J37,K37)) | N37: =IF(J37="","",IF(L37<>"",IF(L37<J37,0,NETWORKDAYS(J37,L37)),IF(G37="Hecho","",IF(Avance!$B$2<J37,0,NETWORKDAYS(J37,Avance!$B$2))))) | O37: =IF(J37="","n/a",IF(L37<>"",L37-K37,IF(G37="Hecho","s/d",MAX(0,Avance!$B$2-K37)))) | P37: =IF(ISNUMBER(O37),ROUND(O37/7,1),O37) | Q37: =IF(J37="","No planificada",IF(G37="Hecho",IF(L37="","Hecha (sin fecha)",IF(L37>K37,"Hecha con atraso","Hecha a tiempo")),IF(Avance!$B$2>K37,"Pendiente atrasada","Pendiente en plazo"))) | R37: HU-01
A38: Sprint 4 | B38: Backend / Firebase | C38: Ingesta: soporte de la sonda DR-ECK1.0, saturación y marca 'fuera de operación' por temperatura | D38: Humberto | E38: 3 | F38: Decoder WQS-LB | G38: Hecho | H38: Commit 2bc34dc (09-oct). [Estimación retroactiva] | I38: Agregada (no planificada) | J38: =IF($I38="Plan original",INDEX('Roadmap Sprints'!$B$2:$B$9,MATCH(IF($A38="Cierre","Semana de cierre",$A38),'Roadmap Sprints'!$A$2:$A$9,0)),"") | K38: =IF($I38="Plan original",INDEX('Roadmap Sprints'!$C$2:$C$9,MATCH(IF($A38="Cierre","Semana de cierre",$A38),'Roadmap Sprints'!$A$2:$A$9,0)),"") | L38: 46304 | M38: =IF(J38="","",NETWORKDAYS(J38,K38)) | N38: =IF(J38="","",IF(L38<>"",IF(L38<J38,0,NETWORKDAYS(J38,L38)),IF(G38="Hecho","",IF(Avance!$B$2<J38,0,NETWORKDAYS(J38,Avance!$B$2))))) | O38: =IF(J38="","n/a",IF(L38<>"",L38-K38,IF(G38="Hecho","s/d",MAX(0,Avance!$B$2-K38)))) | P38: =IF(ISNUMBER(O38),ROUND(O38/7,1),O38) | Q38: =IF(J38="","No planificada",IF(G38="Hecho",IF(L38="","Hecha (sin fecha)",IF(L38>K38,"Hecha con atraso","Hecha a tiempo")),IF(Avance!$B$2>K38,"Pendiente atrasada","Pendiente en plazo"))) | R38: HU-12
A39: Sprint 4 | B39: Backend / Firebase | C39: Procesar el uplink de estado (FPort 5) para conocer el firmware real del nodo | D39: Humberto | E39: 1 | F39: Decoder WQS-LB | G39: Hecho | H39: Commit e90683a (09-oct). Falta recibir el primer FPort 5 real. [Estimación retroactiva] | I39: Agregada (no planificada) | J39: =IF($I39="Plan original",INDEX('Roadmap Sprints'!$B$2:$B$9,MATCH(IF($A39="Cierre","Semana de cierre",$A39),'Roadmap Sprints'!$A$2:$A$9,0)),"") | K39: =IF($I39="Plan original",INDEX('Roadmap Sprints'!$C$2:$C$9,MATCH(IF($A39="Cierre","Semana de cierre",$A39),'Roadmap Sprints'!$A$2:$A$9,0)),"") | L39: 46304 | M39: =IF(J39="","",NETWORKDAYS(J39,K39)) | N39: =IF(J39="","",IF(L39<>"",IF(L39<J39,0,NETWORKDAYS(J39,L39)),IF(G39="Hecho","",IF(Avance!$B$2<J39,0,NETWORKDAYS(J39,Avance!$B$2))))) | O39: =IF(J39="","n/a",IF(L39<>"",L39-K39,IF(G39="Hecho","s/d",MAX(0,Avance!$B$2-K39)))) | P39: =IF(ISNUMBER(O39),ROUND(O39/7,1),O39) | Q39: =IF(J39="","No planificada",IF(G39="Hecho",IF(L39="","Hecha (sin fecha)",IF(L39>K39,"Hecha con atraso","Hecha a tiempo")),IF(Avance!$B$2>K39,"Pendiente atrasada","Pendiente en plazo"))) | R39: HU-10
A40: Sprint 4 | B40: QA / DevOps / Documentación | C40: Guardarraíles de entorno: ningún script toca producción sin flags explícitos | D40: Humberto | E40: 1 | F40: Scripts de seed y simulador | G40: Hecho | H40: Commits 45700b5, 9b5d42f, 16ada9e (09-oct). [Estimación retroactiva] | I40: Agregada (no planificada) | J40: =IF($I40="Plan original",INDEX('Roadmap Sprints'!$B$2:$B$9,MATCH(IF($A40="Cierre","Semana de cierre",$A40),'Roadmap Sprints'!$A$2:$A$9,0)),"") | K40: =IF($I40="Plan original",INDEX('Roadmap Sprints'!$C$2:$C$9,MATCH(IF($A40="Cierre","Semana de cierre",$A40),'Roadmap Sprints'!$A$2:$A$9,0)),"") | L40: 46304 | M40: =IF(J40="","",NETWORKDAYS(J40,K40)) | N40: =IF(J40="","",IF(L40<>"",IF(L40<J40,0,NETWORKDAYS(J40,L40)),IF(G40="Hecho","",IF(Avance!$B$2<J40,0,NETWORKDAYS(J40,Avance!$B$2))))) | O40: =IF(J40="","n/a",IF(L40<>"",L40-K40,IF(G40="Hecho","s/d",MAX(0,Avance!$B$2-K40)))) | P40: =IF(ISNUMBER(O40),ROUND(O40/7,1),O40) | Q40: =IF(J40="","No planificada",IF(G40="Hecho",IF(L40="","Hecha (sin fecha)",IF(L40>K40,"Hecha con atraso","Hecha a tiempo")),IF(Avance!$B$2>K40,"Pendiente atrasada","Pendiente en plazo"))) | R40: HT-04
A41: Sprint 4 | B41: Backend / Firebase | C41: Correcciones de cálculo: compensación de EC, tiempoHastaLimpio y fechas de alertas sin duplicar reintentos | D41: Humberto | E41: 2 | F41: Trigger de cierre de ciclo | G41: Hecho | H41: Commits 32cc5c6, 1190c88, 34b5a9d (09-oct). [Estimación retroactiva] | I41: Agregada (no planificada) | J41: =IF($I41="Plan original",INDEX('Roadmap Sprints'!$B$2:$B$9,MATCH(IF($A41="Cierre","Semana de cierre",$A41),'Roadmap Sprints'!$A$2:$A$9,0)),"") | K41: =IF($I41="Plan original",INDEX('Roadmap Sprints'!$C$2:$C$9,MATCH(IF($A41="Cierre","Semana de cierre",$A41),'Roadmap Sprints'!$A$2:$A$9,0)),"") | L41: 46304 | M41: =IF(J41="","",NETWORKDAYS(J41,K41)) | N41: =IF(J41="","",IF(L41<>"",IF(L41<J41,0,NETWORKDAYS(J41,L41)),IF(G41="Hecho","",IF(Avance!$B$2<J41,0,NETWORKDAYS(J41,Avance!$B$2))))) | O41: =IF(J41="","n/a",IF(L41<>"",L41-K41,IF(G41="Hecho","s/d",MAX(0,Avance!$B$2-K41)))) | P41: =IF(ISNUMBER(O41),ROUND(O41/7,1),O41) | Q41: =IF(J41="","No planificada",IF(G41="Hecho",IF(L41="","Hecha (sin fecha)",IF(L41>K41,"Hecha con atraso","Hecha a tiempo")),IF(Avance!$B$2>K41,"Pendiente atrasada","Pendiente en plazo"))) | R41: HU-06
A42: Sprint 4 | B42: Análisis Predictivo | C42: Simulador de ciclo CIP (modelo de etapas, codificador WQS, estadoProceso y comando sim:cip) | D42: Humberto | E42: 4 | F42: Decoder WQS-LB | G42: Hecho | H42: Commits df1a660, 8a263a1 (09/14-oct). Sirve para la demo; es la base para emular datos para ML. [Estimación retroactiva] | I42: Agregada (no planificada) | J42: =IF($I42="Plan original",INDEX('Roadmap Sprints'!$B$2:$B$9,MATCH(IF($A42="Cierre","Semana de cierre",$A42),'Roadmap Sprints'!$A$2:$A$9,0)),"") | K42: =IF($I42="Plan original",INDEX('Roadmap Sprints'!$C$2:$C$9,MATCH(IF($A42="Cierre","Semana de cierre",$A42),'Roadmap Sprints'!$A$2:$A$9,0)),"") | L42: 46309 | M42: =IF(J42="","",NETWORKDAYS(J42,K42)) | N42: =IF(J42="","",IF(L42<>"",IF(L42<J42,0,NETWORKDAYS(J42,L42)),IF(G42="Hecho","",IF(Avance!$B$2<J42,0,NETWORKDAYS(J42,Avance!$B$2))))) | O42: =IF(J42="","n/a",IF(L42<>"",L42-K42,IF(G42="Hecho","s/d",MAX(0,Avance!$B$2-K42)))) | P42: =IF(ISNUMBER(O42),ROUND(O42/7,1),O42) | Q42: =IF(J42="","No planificada",IF(G42="Hecho",IF(L42="","Hecha (sin fecha)",IF(L42>K42,"Hecha con atraso","Hecha a tiempo")),IF(Avance!$B$2>K42,"Pendiente atrasada","Pendiente en plazo"))) | R42: HU-11
A43: Sprint 4 | B43: QA / DevOps / Documentación | C43: Documento PENDIENTES-DASHBOARD.md con los hallazgos de la revisión (15 puntos) | D43: Humberto | E43: 1 | F43: - | G43: Hecho | H43: Commit 4eb3754 (09-oct). [Estimación retroactiva] | I43: Agregada (no planificada) | J43: =IF($I43="Plan original",INDEX('Roadmap Sprints'!$B$2:$B$9,MATCH(IF($A43="Cierre","Semana de cierre",$A43),'Roadmap Sprints'!$A$2:$A$9,0)),"") | K43: =IF($I43="Plan original",INDEX('Roadmap Sprints'!$C$2:$C$9,MATCH(IF($A43="Cierre","Semana de cierre",$A43),'Roadmap Sprints'!$A$2:$A$9,0)),"") | L43: 46304 | M43: =IF(J43="","",NETWORKDAYS(J43,K43)) | N43: =IF(J43="","",IF(L43<>"",IF(L43<J43,0,NETWORKDAYS(J43,L43)),IF(G43="Hecho","",IF(Avance!$B$2<J43,0,NETWORKDAYS(J43,Avance!$B$2))))) | O43: =IF(J43="","n/a",IF(L43<>"",L43-K43,IF(G43="Hecho","s/d",MAX(0,Avance!$B$2-K43)))) | P43: =IF(ISNUMBER(O43),ROUND(O43/7,1),O43) | Q43: =IF(J43="","No planificada",IF(G43="Hecho",IF(L43="","Hecha (sin fecha)",IF(L43>K43,"Hecha con atraso","Hecha a tiempo")),IF(Avance!$B$2>K43,"Pendiente atrasada","Pendiente en plazo"))) | R43: HT-05
A44: Sprint 4 | B44: Frontend / Dashboard | C44: Tarjetas del dashboard según las sondas del equipo (catálogo, saturación '≥ tope') | D44: Humberto | E44: 3 | F44: Soporte DR-ECK1.0 | G44: Hecho | H44: Commits 75dc826, 3403df8, 06d562c (14-oct). [Estimación retroactiva] | I44: Agregada (no planificada) | J44: =IF($I44="Plan original",INDEX('Roadmap Sprints'!$B$2:$B$9,MATCH(IF($A44="Cierre","Semana de cierre",$A44),'Roadmap Sprints'!$A$2:$A$9,0)),"") | K44: =IF($I44="Plan original",INDEX('Roadmap Sprints'!$C$2:$C$9,MATCH(IF($A44="Cierre","Semana de cierre",$A44),'Roadmap Sprints'!$A$2:$A$9,0)),"") | L44: 46309 | M44: =IF(J44="","",NETWORKDAYS(J44,K44)) | N44: =IF(J44="","",IF(L44<>"",IF(L44<J44,0,NETWORKDAYS(J44,L44)),IF(G44="Hecho","",IF(Avance!$B$2<J44,0,NETWORKDAYS(J44,Avance!$B$2))))) | O44: =IF(J44="","n/a",IF(L44<>"",L44-K44,IF(G44="Hecho","s/d",MAX(0,Avance!$B$2-K44)))) | P44: =IF(ISNUMBER(O44),ROUND(O44/7,1),O44) | Q44: =IF(J44="","No planificada",IF(G44="Hecho",IF(L44="","Hecha (sin fecha)",IF(L44>K44,"Hecha con atraso","Hecha a tiempo")),IF(Avance!$B$2>K44,"Pendiente atrasada","Pendiente en plazo"))) | R44: HU-01
A45: Sprint 4 | B45: Frontend / Dashboard | C45: Barra de etapas con tiempo restante y gráfico de tendencia con eje de tiempo, franjas por etapa y confianza por punto | D45: Humberto | E45: 4 | F45: Simulador de ciclo CIP | G45: Hecho | H45: Commits c243adf, a71fddf, 9ea5933, f4a9fc9, 973cc80 (14-oct). [Estimación retroactiva] | I45: Agregada (no planificada) | J45: =IF($I45="Plan original",INDEX('Roadmap Sprints'!$B$2:$B$9,MATCH(IF($A45="Cierre","Semana de cierre",$A45),'Roadmap Sprints'!$A$2:$A$9,0)),"") | K45: =IF($I45="Plan original",INDEX('Roadmap Sprints'!$C$2:$C$9,MATCH(IF($A45="Cierre","Semana de cierre",$A45),'Roadmap Sprints'!$A$2:$A$9,0)),"") | L45: 46309 | M45: =IF(J45="","",NETWORKDAYS(J45,K45)) | N45: =IF(J45="","",IF(L45<>"",IF(L45<J45,0,NETWORKDAYS(J45,L45)),IF(G45="Hecho","",IF(Avance!$B$2<J45,0,NETWORKDAYS(J45,Avance!$B$2))))) | O45: =IF(J45="","n/a",IF(L45<>"",L45-K45,IF(G45="Hecho","s/d",MAX(0,Avance!$B$2-K45)))) | P45: =IF(ISNUMBER(O45),ROUND(O45/7,1),O45) | Q45: =IF(J45="","No planificada",IF(G45="Hecho",IF(L45="","Hecha (sin fecha)",IF(L45>K45,"Hecha con atraso","Hecha a tiempo")),IF(Avance!$B$2>K45,"Pendiente atrasada","Pendiente en plazo"))) | R45: HU-02
A46: Sprint 4 | B46: Frontend / Dashboard | C46: Control de la simulación desde el dashboard (botón de demo, selector de línea) y reglas de Firestore asociadas | D46: Humberto | E46: 3 | F46: Simulador de ciclo CIP | G46: Hecho | H46: Commits bec9f20, 67284b7, 1577029, c13c2fc (14-oct). [Estimación retroactiva] | I46: Agregada (no planificada) | J46: =IF($I46="Plan original",INDEX('Roadmap Sprints'!$B$2:$B$9,MATCH(IF($A46="Cierre","Semana de cierre",$A46),'Roadmap Sprints'!$A$2:$A$9,0)),"") | K46: =IF($I46="Plan original",INDEX('Roadmap Sprints'!$C$2:$C$9,MATCH(IF($A46="Cierre","Semana de cierre",$A46),'Roadmap Sprints'!$A$2:$A$9,0)),"") | L46: 46309 | M46: =IF(J46="","",NETWORKDAYS(J46,K46)) | N46: =IF(J46="","",IF(L46<>"",IF(L46<J46,0,NETWORKDAYS(J46,L46)),IF(G46="Hecho","",IF(Avance!$B$2<J46,0,NETWORKDAYS(J46,Avance!$B$2))))) | O46: =IF(J46="","n/a",IF(L46<>"",L46-K46,IF(G46="Hecho","s/d",MAX(0,Avance!$B$2-K46)))) | P46: =IF(ISNUMBER(O46),ROUND(O46/7,1),O46) | Q46: =IF(J46="","No planificada",IF(G46="Hecho",IF(L46="","Hecha (sin fecha)",IF(L46>K46,"Hecha con atraso","Hecha a tiempo")),IF(Avance!$B$2>K46,"Pendiente atrasada","Pendiente en plazo"))) | R46: HU-11
... A48: Sprint 4 | B48: QA / DevOps / Documentación | C48: Documentar el despliegue a producción (orden reglas, funciones, Hosting) y errores comunes en el README | D48: Humberto | E48: 1 | F48: Despliegue preparado | G48: Hecho | H48: Commits c4dc66f, 0c52265 (14-oct). [Estimación retroactiva] | I48: Agregada (no planificada) | J48: =IF($I48="Plan original",INDEX('Roadmap Sprints'!$B$2:$B$9,MATCH(IF($A48="Cierre","Semana de cierre",$A48),'Roadmap Sprints'!$A$2:$A$9,0)),"") | K48: =IF($I48="Plan original",INDEX('Roadmap Sprints'!$C$2:$C$9,MATCH(IF($A48="Cierre","Semana de cierre",$A48),'Roadmap Sprints'!$A$2:$A$9,0)),"") | L48: 46309 | M48: =IF(J48="","",NETWORKDAYS(J48,K48)) | N48: =IF(J48="","",IF(L48<>"",IF(L48<J48,0,NETWORKDAYS(J48,L48)),IF(G48="Hecho","",IF(Avance!$B$2<J48,0,NETWORKDAYS(J48,Avance!$B$2))))) | O48: =IF(J48="","n/a",IF(L48<>"",L48-K48,IF(G48="Hecho","s/d",MAX(0,Avance!$B$2-K48)))) | P48: =IF(ISNUMBER(O48),ROUND(O48/7,1),O48) | Q48: =IF(J48="","No planificada",IF(G48="Hecho",IF(L48="","Hecha (sin fecha)",IF(L48>K48,"Hecha con atraso","Hecha a tiempo")),IF(Avance!$B$2>K48,"Pendiente atrasada","Pendiente en plazo"))) | R48: HT-01
A49: Sprint 4 | B49: Análisis Predictivo | C49: Revisar manuales de los sensores comprados y datos típicos de un CIP para emular datos y configurar los modelos de predicción | D49: Equipo | E49: 3 | F49: Orden de compra de sensores | G49: En proceso | H49: Iniciada el 18-oct-2026 mientras el técnico arma el prototipo. Insumo de las filas de diseño de simulación, dataset simulado y primer modelo ML. | I49: Agregada (no planificada) | J49: =IF($I49="Plan original",INDEX('Roadmap Sprints'!$B$2:$B$9,MATCH(IF($A49="Cierre","Semana de cierre",$A49),'Roadmap Sprints'!$A$2:$A$9,0)),"") | K49: =IF($I49="Plan original",INDEX('Roadmap Sprints'!$C$2:$C$9,MATCH(IF($A49="Cierre","Semana de cierre",$A49),'Roadmap Sprints'!$A$2:$A$9,0)),"") | M49: =IF(J49="","",NETWORKDAYS(J49,K49)) | N49: =IF(J49="","",IF(L49<>"",IF(L49<J49,0,NETWORKDAYS(J49,L49)),IF(G49="Hecho","",IF(Avance!$B$2<J49,0,NETWORKDAYS(J49,Avance!$B$2))))) | O49: =IF(J49="","n/a",IF(L49<>"",L49-K49,IF(G49="Hecho","s/d",MAX(0,Avance!$B$2-K49)))) | P49: =IF(ISNUMBER(O49),ROUND(O49/7,1),O49) | Q49: =IF(J49="","No planificada",IF(G49="Hecho",IF(L49="","Hecha (sin fecha)",IF(L49>K49,"Hecha con atraso","Hecha a tiempo")),IF(Avance!$B$2>K49,"Pendiente atrasada","Pendiente en plazo"))) | R49: HU-07
A50: Sprint 5 | B50: Hardware / Sensores | C50: Integración de sensor de conductividad y caudalímetro (agua/químicos) | D50: Técnico | E50: 5 | F50: Calibración inicial | G50: Por hacer | H50: Manual del flujómetro SW3L-LB pendiente y rango de temperatura a verificar (PENDIENTES-DASHBOARD.md §7). | I50: Plan original | J50: =IF($I50="Plan original",INDEX('Roadmap Sprints'!$B$2:$B$9,MATCH(IF($A50="Cierre","Semana de cierre",$A50),'Roadmap Sprints'!$A$2:$A$9,0)),"") | K50: =IF($I50="Plan original",INDEX('Roadmap Sprints'!$C$2:$C$9,MATCH(IF($A50="Cierre","Semana de cierre",$A50),'Roadmap Sprints'!$A$2:$A$9,0)),"") | M50: =IF(J50="","",NETWORKDAYS(J50,K50)) | N50: =IF(J50="","",IF(L50<>"",IF(L50<J50,0,NETWORKDAYS(J50,L50)),IF(G50="Hecho","",IF(Avance!$B$2<J50,0,NETWORKDAYS(J50,Avance!$B$2))))) | O50: =IF(J50="","n/a",IF(L50<>"",L50-K50,IF(G50="Hecho","s/d",MAX(0,Avance!$B$2-K50)))) | P50: =IF(ISNUMBER(O50),ROUND(O50/7,1),O50) | Q50: =IF(J50="","No planificada",IF(G50="Hecho",IF(L50="","Hecha (sin fecha)",IF(L50>K50,"Hecha con atraso","Hecha a tiempo")),IF(Avance!$B$2>K50,"Pendiente atrasada","Pendiente en plazo"))) | R50: HU-05
A51: Sprint 5 | B51: Backend / Firebase | C51: Cálculo de consumo de agua y químicos a partir de lecturas de caudal | D51: Dev Backend | E51: 4 | F51: Sensor de caudal integrado | G51: En proceso | H51: volumenEstimado con caudal nominal de la bomba (no hay caudalímetro en la planta); consumo de químicos no calculado. | I51: Plan original | J51: =IF($I51="Plan original",INDEX('Roadmap Sprints'!$B$2:$B$9,MATCH(IF($A51="Cierre","Semana de cierre",$A51),'Roadmap Sprints'!$A$2:$A$9,0)),"") | K51: =IF($I51="Plan original",INDEX('Roadmap Sprints'!$C$2:$C$9,MATCH(IF($A51="Cierre","Semana de cierre",$A51),'Roadmap Sprints'!$A$2:$A$9,0)),"") | M51: =IF(J51="","",NETWORKDAYS(J51,K51)) | N51: =IF(J51="","",IF(L51<>"",IF(L51<J51,0,NETWORKDAYS(J51,L51)),IF(G51="Hecho","",IF(Avance!$B$2<J51,0,NETWORKDAYS(J51,Avance!$B$2))))) | O51: =IF(J51="","n/a",IF(L51<>"",L51-K51,IF(G51="Hecho","s/d",MAX(0,Avance!$B$2-K51)))) | P51: =IF(ISNUMBER(O51),ROUND(O51/7,1),O51) | Q51: =IF(J51="","No planificada",IF(G51="Hecho",IF(L51="","Hecha (sin fecha)",IF(L51>K51,"Hecha con atraso","Hecha a tiempo")),IF(Avance!$B$2>K51,"Pendiente atrasada","Pendiente en plazo"))) | R51: HU-05
A52: Sprint 5 | B52: Frontend / Dashboard | C52: Panel de consumo de químicos y agua (totales y tendencia) | D52: Dev Frontend | E52: 5 | F52: Cálculo de consumo | G52: En proceso | H52: Indicadores del ciclo con volumen estimado en el dashboard; el panel dedicado de consumo aún no existe. | I52: Plan original | J52: =IF($I52="Plan original",INDEX('Roadmap Sprints'!$B$2:$B$9,MATCH(IF($A52="Cierre","Semana de cierre",$A52),'Roadmap Sprints'!$A$2:$A$9,0)),"") | K52: =IF($I52="Plan original",INDEX('Roadmap Sprints'!$C$2:$C$9,MATCH(IF($A52="Cierre","Semana de cierre",$A52),'Roadmap Sprints'!$A$2:$A$9,0)),"") | M52: =IF(J52="","",NETWORKDAYS(J52,K52)) | N52: =IF(J52="","",IF(L52<>"",IF(L52<J52,0,NETWORKDAYS(J52,L52)),IF(G52="Hecho","",IF(Avance!$B$2<J52,0,NETWORKDAYS(J52,Avance!$B$2))))) | O52: =IF(J52="","n/a",IF(L52<>"",L52-K52,IF(G52="Hecho","s/d",MAX(0,Avance!$B$2-K52)))) | P52: =IF(ISNUMBER(O52),ROUND(O52/7,1),O52) | Q52: =IF(J52="","No planificada",IF(G52="Hecho",IF(L52="","Hecha (sin fecha)",IF(L52>K52,"Hecha con atraso","Hecha a tiempo")),IF(Avance!$B$2>K52,"Pendiente atrasada","Pendiente en plazo"))) | R52: HU-05
A53: Sprint 5 | B53: Frontend / Dashboard | C53: Vista de históricos básicos (últimas 24h / 7 días) por variable | D53: Dev Frontend | E53: 4 | F53: Datos almacenados en Firestore | G53: Por hacer | H53: La vista /historial es un placeholder; el índice COLLECTION_GROUP de lecturas no está desplegado. | I53: Plan original | J53: =IF($I53="Plan original",INDEX('Roadmap Sprints'!$B$2:$B$9,MATCH(IF($A53="Cierre","Semana de cierre",$A53),'Roadmap Sprints'!$A$2:$A$9,0)),"") | K53: =IF($I53="Plan original",INDEX('Roadmap Sprints'!$C$2:$C$9,MATCH(IF($A53="Cierre","Semana de cierre",$A53),'Roadmap Sprints'!$A$2:$A$9,0)),"") | M53: =IF(J53="","",NETWORKDAYS(J53,K53)) | N53: =IF(J53="","",IF(L53<>"",IF(L53<J53,0,NETWORKDAYS(J53,L53)),IF(G53="Hecho","",IF(Avance!$B$2<J53,0,NETWORKDAYS(J53,Avance!$B$2))))) | O53: =IF(J53="","n/a",IF(L53<>"",L53-K53,IF(G53="Hecho","s/d",MAX(0,Avance!$B$2-K53)))) | P53: =IF(ISNUMBER(O53),ROUND(O53/7,1),O53) | Q53: =IF(J53="","No planificada",IF(G53="Hecho",IF(L53="","Hecha (sin fecha)",IF(L53>K53,"Hecha con atraso","Hecha a tiempo")),IF(Avance!$B$2>K53,"Pendiente atrasada","Pendiente en plazo"))) | R53: HU-04
A54: Sprint 5 | B54: Análisis Predictivo | C54: Empezar a recalibrar/re-entrenar los modelos ML con los primeros datos reales que ya entrega la maqueta | D54: Dev Backend | E54: 4 | F54: Datos reales acumulados de la maqueta | G54: Por hacer | I54: Plan original | J54: =IF($I54="Plan original",INDEX('Roadmap Sprints'!$B$2:$B$9,MATCH(IF($A54="Cierre","Semana de cierre",$A54),'Roadmap Sprints'!$A$2:$A$9,0)),"") | K54: =IF($I54="Plan original",INDEX('Roadmap Sprints'!$C$2:$C$9,MATCH(IF($A54="Cierre","Semana de cierre",$A54),'Roadmap Sprints'!$A$2:$A$9,0)),"") | M54: =IF(J54="","",NETWORKDAYS(J54,K54)) | N54: =IF(J54="","",IF(L54<>"",IF(L54<J54,0,NETWORKDAYS(J54,L54)),IF(G54="Hecho","",IF(Avance!$B$2<J54,0,NETWORKDAYS(J54,Avance!$B$2))))) | O54: =IF(J54="","n/a",IF(L54<>"",L54-K54,IF(G54="Hecho","s/d",MAX(0,Avance!$B$2-K54)))) | P54: =IF(ISNUMBER(O54),ROUND(O54/7,1),O54) | Q54: =IF(J54="","No planificada",IF(G54="Hecho",IF(L54="","Hecha (sin fecha)",IF(L54>K54,"Hecha con atraso","Hecha a tiempo")),IF(Avance!$B$2>K54,"Pendiente atrasada","Pendiente en plazo"))) | R54: HU-07
A55: Sprint 6 | B55: Auth / Seguridad | C55: Reglas de seguridad de Firestore por rol (cliente vs. interno) | D55: Dev Auth | E55: 4 | F55: Roles definidos | G55: En proceso | H55: Reglas por rol y tests de reglas hechos; falta limitar los campos que puede escribir el operador (PENDIENTES §9). | I55: Plan original | J55: =IF($I55="Plan original",INDEX('Roadmap Sprints'!$B$2:$B$9,MATCH(IF($A55="Cierre","Semana de cierre",$A55),'Roadmap Sprints'!$A$2:$A$9,0)),"") | K55: =IF($I55="Plan original",INDEX('Roadmap Sprints'!$C$2:$C$9,MATCH(IF($A55="Cierre","Semana de cierre",$A55),'Roadmap Sprints'!$A$2:$A$9,0)),"") | M55: =IF(J55="","",NETWORKDAYS(J55,K55)) | N55: =IF(J55="","",IF(L55<>"",IF(L55<J55,0,NETWORKDAYS(J55,L55)),IF(G55="Hecho","",IF(Avance!$B$2<J55,0,NETWORKDAYS(J55,Avance!$B$2))))) | O55: =IF(J55="","n/a",IF(L55<>"",L55-K55,IF(G55="Hecho","s/d",MAX(0,Avance!$B$2-K55)))) | P55: =IF(ISNUMBER(O55),ROUND(O55/7,1),O55) | Q55: =IF(J55="","No planificada",IF(G55="Hecho",IF(L55="","Hecha (sin fecha)",IF(L55>K55,"Hecha con atraso","Hecha a tiempo")),IF(Avance!$B$2>K55,"Pendiente atrasada","Pendiente en plazo"))) | R55: HU-08
A56: Sprint 6 | B56: Auth / Seguridad | C56: Pantallas y permisos diferenciados por rol de usuario | D56: Dev Frontend | E56: 4 | F56: Reglas de seguridad | G56: En proceso | H56: GuardRol implementado; hoy el dashboard es solo para admin, faltan las vistas de operador/visor (rol cliente). | I56: Plan original | J56: =IF($I56="Plan original",INDEX('Roadmap Sprints'!$B$2:$B$9,MATCH(IF($A56="Cierre","Semana de cierre",$A56),'Roadmap Sprints'!$A$2:$A$9,0)),"") | K56: =IF($I56="Plan original",INDEX('Roadmap Sprints'!$C$2:$C$9,MATCH(IF($A56="Cierre","Semana de cierre",$A56),'Roadmap Sprints'!$A$2:$A$9,0)),"") | M56: =IF(J56="","",NETWORKDAYS(J56,K56)) | N56: =IF(J56="","",IF(L56<>"",IF(L56<J56,0,NETWORKDAYS(J56,L56)),IF(G56="Hecho","",IF(Avance!$B$2<J56,0,NETWORKDAYS(J56,Avance!$B$2))))) | O56: =IF(J56="","n/a",IF(L56<>"",L56-K56,IF(G56="Hecho","s/d",MAX(0,Avance!$B$2-K56)))) | P56: =IF(ISNUMBER(O56),ROUND(O56/7,1),O56) | Q56: =IF(J56="","No planificada",IF(G56="Hecho",IF(L56="","Hecha (sin fecha)",IF(L56>K56,"Hecha con atraso","Hecha a tiempo")),IF(Avance!$B$2>K56,"Pendiente atrasada","Pendiente en plazo"))) | R56: HU-08
A57: Sprint 6 | B57: Backend / Firebase | C57: Manejo de errores y reconexión ante pérdida de señal de sensores | D57: Dev Backend | E57: 4 | F57: Pipeline de ingesta estable | G57: En proceso | H57: Hecho: idempotencia de lecturas, validación de payload y detección de equipo sin datos. Falta buffer local en el gateway. | I57: Plan original | J57: =IF($I57="Plan original",INDEX('Roadmap Sprints'!$B$2:$B$9,MATCH(IF($A57="Cierre","Semana de cierre",$A57),'Roadmap Sprints'!$A$2:$A$9,0)),"") | K57: =IF($I57="Plan original",INDEX('Roadmap Sprints'!$C$2:$C$9,MATCH(IF($A57="Cierre","Semana de cierre",$A57),'Roadmap Sprints'!$A$2:$A$9,0)),"") | M57: =IF(J57="","",NETWORKDAYS(J57,K57)) | N57: =IF(J57="","",IF(L57<>"",IF(L57<J57,0,NETWORKDAYS(J57,L57)),IF(G57="Hecho","",IF(Avance!$B$2<J57,0,NETWORKDAYS(J57,Avance!$B$2))))) | O57: =IF(J57="","n/a",IF(L57<>"",L57-K57,IF(G57="Hecho","s/d",MAX(0,Avance!$B$2-K57)))) | P57: =IF(ISNUMBER(O57),ROUND(O57/7,1),O57) | Q57: =IF(J57="","No planificada",IF(G57="Hecho",IF(L57="","Hecha (sin fecha)",IF(L57>K57,"Hecha con atraso","Hecha a tiempo")),IF(Avance!$B$2>K57,"Pendiente atrasada","Pendiente en plazo"))) | R57: HU-12
A58: Sprint 6 | B58: Hardware / Sensores | C58: Prueba de estabilidad de la maqueta en jornada prolongada (8h+) | D58: Técnico | E58: 3 | F58: Todos los sensores integrados | G58: Por hacer | I58: Plan original | J58: =IF($I58="Plan original",INDEX('Roadmap Sprints'!$B$2:$B$9,MATCH(IF($A58="Cierre","Semana de cierre",$A58),'Roadmap Sprints'!$A$2:$A$9,0)),"") | K58: =IF($I58="Plan original",INDEX('Roadmap Sprints'!$C$2:$C$9,MATCH(IF($A58="Cierre","Semana de cierre",$A58),'Roadmap Sprints'!$A$2:$A$9,0)),"") | M58: =IF(J58="","",NETWORKDAYS(J58,K58)) | N58: =IF(J58="","",IF(L58<>"",IF(L58<J58,0,NETWORKDAYS(J58,L58)),IF(G58="Hecho","",IF(Avance!$B$2<J58,0,NETWORKDAYS(J58,Avance!$B$2))))) | O58: =IF(J58="","n/a",IF(L58<>"",L58-K58,IF(G58="Hecho","s/d",MAX(0,Avance!$B$2-K58)))) | P58: =IF(ISNUMBER(O58),ROUND(O58/7,1),O58) | Q58: =IF(J58="","No planificada",IF(G58="Hecho",IF(L58="","Hecha (sin fecha)",IF(L58>K58,"Hecha con atraso","Hecha a tiempo")),IF(Avance!$B$2>K58,"Pendiente atrasada","Pendiente en plazo"))) | R58: HT-03
A59: Sprint 6 | B59: Análisis Predictivo | C59: Validar precisión/utilidad de los modelos ML contra los datos reales acumulados y ajustar | D59: Dev Backend | E59: 4 | F59: Modelos recalibrados | G59: Por hacer | I59: Plan original | J59: =IF($I59="Plan original",INDEX('Roadmap Sprints'!$B$2:$B$9,MATCH(IF($A59="Cierre","Semana de cierre",$A59),'Roadmap Sprints'!$A$2:$A$9,0)),"") | K59: =IF($I59="Plan original",INDEX('Roadmap Sprints'!$C$2:$C$9,MATCH(IF($A59="Cierre","Semana de cierre",$A59),'Roadmap Sprints'!$A$2:$A$9,0)),"") | M59: =IF(J59="","",NETWORKDAYS(J59,K59)) | N59: =IF(J59="","",IF(L59<>"",IF(L59<J59,0,NETWORKDAYS(J59,L59)),IF(G59="Hecho","",IF(Avance!$B$2<J59,0,NETWORKDAYS(J59,Avance!$B$2))))) | O59: =IF(J59="","n/a",IF(L59<>"",L59-K59,IF(G59="Hecho","s/d",MAX(0,Avance!$B$2-K59)))) | P59: =IF(ISNUMBER(O59),ROUND(O59/7,1),O59) | Q59: =IF(J59="","No planificada",IF(G59="Hecho",IF(L59="","Hecha (sin fecha)",IF(L59>K59,"Hecha con atraso","Hecha a tiempo")),IF(Avance!$B$2>K59,"Pendiente atrasada","Pendiente en plazo"))) | R59: HU-07
A60: Sprint 6 | B60: Análisis Predictivo | C60: Pulir el panel de análisis predictivo en el dashboard (mensajes claros de proyección/alerta) | D60: Dev Frontend | E60: 3 | F60: Modelos validados | G60: Por hacer | I60: Plan original | J60: =IF($I60="Plan original",INDEX('Roadmap Sprints'!$B$2:$B$9,MATCH(IF($A60="Cierre","Semana de cierre",$A60),'Roadmap Sprints'!$A$2:$A$9,0)),"") | K60: =IF($I60="Plan original",INDEX('Roadmap Sprints'!$C$2:$C$9,MATCH(IF($A60="Cierre","Semana de cierre",$A60),'Roadmap Sprints'!$A$2:$A$9,0)),"") | M60: =IF(J60="","",NETWORKDAYS(J60,K60)) | N60: =IF(J60="","",IF(L60<>"",IF(L60<J60,0,NETWORKDAYS(J60,L60)),IF(G60="Hecho","",IF(Avance!$B$2<J60,0,NETWORKDAYS(J60,Avance!$B$2))))) | O60: =IF(J60="","n/a",IF(L60<>"",L60-K60,IF(G60="Hecho","s/d",MAX(0,Avance!$B$2-K60)))) | P60: =IF(ISNUMBER(O60),ROUND(O60/7,1),O60) | Q60: =IF(J60="","No planificada",IF(G60="Hecho",IF(L60="","Hecha (sin fecha)",IF(L60>K60,"Hecha con atraso","Hecha a tiempo")),IF(Avance!$B$2>K60,"Pendiente atrasada","Pendiente en plazo"))) | R60: HU-07
A61: Sprint 7 | B61: QA / DevOps / Documentación | C61: Pruebas end-to-end e integrales de todo el flujo de datos | D61: Equipo completo | E61: 4 | F61: Pipeline completo | G61: Por hacer | I61: Plan original | J61: =IF($I61="Plan original",INDEX('Roadmap Sprints'!$B$2:$B$9,MATCH(IF($A61="Cierre","Semana de cierre",$A61),'Roadmap Sprints'!$A$2:$A$9,0)),"") | K61: =IF($I61="Plan original",INDEX('Roadmap Sprints'!$C$2:$C$9,MATCH(IF($A61="Cierre","Semana de cierre",$A61),'Roadmap Sprints'!$A$2:$A$9,0)),"") | M61: =IF(J61="","",NETWORKDAYS(J61,K61)) | N61: =IF(J61="","",IF(L61<>"",IF(L61<J61,0,NETWORKDAYS(J61,L61)),IF(G61="Hecho","",IF(Avance!$B$2<J61,0,NETWORKDAYS(J61,Avance!$B$2))))) | O61: =IF(J61="","n/a",IF(L61<>"",L61-K61,IF(G61="Hecho","s/d",MAX(0,Avance!$B$2-K61)))) | P61: =IF(ISNUMBER(O61),ROUND(O61/7,1),O61) | Q61: =IF(J61="","No planificada",IF(G61="Hecho",IF(L61="","Hecha (sin fecha)",IF(L61>K61,"Hecha con atraso","Hecha a tiempo")),IF(Avance!$B$2>K61,"Pendiente atrasada","Pendiente en plazo"))) | R61: HT-04
A62: Sprint 7 | B62: QA / DevOps / Documentación | C62: Pruebas de carga con flujo continuo/masivo de datos de sensores | D62: Dev Backend | E62: 3 | F62: Pipeline completo | G62: Por hacer | I62: Plan original | J62: =IF($I62="Plan original",INDEX('Roadmap Sprints'!$B$2:$B$9,MATCH(IF($A62="Cierre","Semana de cierre",$A62),'Roadmap Sprints'!$A$2:$A$9,0)),"") | K62: =IF($I62="Plan original",INDEX('Roadmap Sprints'!$C$2:$C$9,MATCH(IF($A62="Cierre","Semana de cierre",$A62),'Roadmap Sprints'!$A$2:$A$9,0)),"") | M62: =IF(J62="","",NETWORKDAYS(J62,K62)) | N62: =IF(J62="","",IF(L62<>"",IF(L62<J62,0,NETWORKDAYS(J62,L62)),IF(G62="Hecho","",IF(Avance!$B$2<J62,0,NETWORKDAYS(J62,Avance!$B$2))))) | O62: =IF(J62="","n/a",IF(L62<>"",L62-K62,IF(G62="Hecho","s/d",MAX(0,Avance!$B$2-K62)))) | P62: =IF(ISNUMBER(O62),ROUND(O62/7,1),O62) | Q62: =IF(J62="","No planificada",IF(G62="Hecho",IF(L62="","Hecha (sin fecha)",IF(L62>K62,"Hecha con atraso","Hecha a tiempo")),IF(Avance!$B$2>K62,"Pendiente atrasada","Pendiente en plazo"))) | R62: HT-04
A63: Sprint 7 | B63: QA / DevOps / Documentación | C63: Corrección de bugs detectados en pruebas | D63: Equipo completo | E63: 4 | F63: Resultados de pruebas | G63: Por hacer | I63: Plan original | J63: =IF($I63="Plan original",INDEX('Roadmap Sprints'!$B$2:$B$9,MATCH(IF($A63="Cierre","Semana de cierre",$A63),'Roadmap Sprints'!$A$2:$A$9,0)),"") | K63: =IF($I63="Plan original",INDEX('Roadmap Sprints'!$C$2:$C$9,MATCH(IF($A63="Cierre","Semana de cierre",$A63),'Roadmap Sprints'!$A$2:$A$9,0)),"") | M63: =IF(J63="","",NETWORKDAYS(J63,K63)) | N63: =IF(J63="","",IF(L63<>"",IF(L63<J63,0,NETWORKDAYS(J63,L63)),IF(G63="Hecho","",IF(Avance!$B$2<J63,0,NETWORKDAYS(J63,Avance!$B$2))))) | O63: =IF(J63="","n/a",IF(L63<>"",L63-K63,IF(G63="Hecho","s/d",MAX(0,Avance!$B$2-K63)))) | P63: =IF(ISNUMBER(O63),ROUND(O63/7,1),O63) | Q63: =IF(J63="","No planificada",IF(G63="Hecho",IF(L63="","Hecha (sin fecha)",IF(L63>K63,"Hecha con atraso","Hecha a tiempo")),IF(Avance!$B$2>K63,"Pendiente atrasada","Pendiente en plazo"))) | R63: HT-04
A64: Sprint 7 | B64: QA / DevOps / Documentación | C64: Documentación técnica (arquitectura, despliegue) y manual de usuario | D64: Equipo completo | E64: 3 | F64: - | G64: En proceso | H64: Hecho: README, DESPLIEGUE.md, SPRINT1/3.md, EXPLICACION-SISTEMA-SENSORES.md. Falta el manual de usuario. | I64: Plan original | J64: =IF($I64="Plan original",INDEX('Roadmap Sprints'!$B$2:$B$9,MATCH(IF($A64="Cierre","Semana de cierre",$A64),'Roadmap Sprints'!$A$2:$A$9,0)),"") | K64: =IF($I64="Plan original",INDEX('Roadmap Sprints'!$C$2:$C$9,MATCH(IF($A64="Cierre","Semana de cierre",$A64),'Roadmap Sprints'!$A$2:$A$9,0)),"") | M64: =IF(J64="","",NETWORKDAYS(J64,K64)) | N64: =IF(J64="","",IF(L64<>"",IF(L64<J64,0,NETWORKDAYS(J64,L64)),IF(G64="Hecho","",IF(Avance!$B$2<J64,0,NETWORKDAYS(J64,Avance!$B$2))))) | O64: =IF(J64="","n/a",IF(L64<>"",L64-K64,IF(G64="Hecho","s/d",MAX(0,Avance!$B$2-K64)))) | P64: =IF(ISNUMBER(O64),ROUND(O64/7,1),O64) | Q64: =IF(J64="","No planificada",IF(G64="Hecho",IF(L64="","Hecha (sin fecha)",IF(L64>K64,"Hecha con atraso","Hecha a tiempo")),IF(Avance!$B$2>K64,"Pendiente atrasada","Pendiente en plazo"))) | R64: HT-05
A65: Sprint 7 | B65: Backend / Firebase | C65: Despliegue a ambiente estable/producción en Firebase Hosting | D65: Dev Backend | E65: 2 | F65: Bugs corregidos | G65: En proceso | H65: Ya hay un despliegue en producción (stormcip-972bd); falta el despliegue de la versión final y un staging. | I65: Plan original | J65: =IF($I65="Plan original",INDEX('Roadmap Sprints'!$B$2:$B$9,MATCH(IF($A65="Cierre","Semana de cierre",$A65),'Roadmap Sprints'!$A$2:$A$9,0)),"") | K65: =IF($I65="Plan original",INDEX('Roadmap Sprints'!$C$2:$C$9,MATCH(IF($A65="Cierre","Semana de cierre",$A65),'Roadmap Sprints'!$A$2:$A$9,0)),"") | M65: =IF(J65="","",NETWORKDAYS(J65,K65)) | N65: =IF(J65="","",IF(L65<>"",IF(L65<J65,0,NETWORKDAYS(J65,L65)),IF(G65="Hecho","",IF(Avance!$B$2<J65,0,NETWORKDAYS(J65,Avance!$B$2))))) | O65: =IF(J65="","n/a",IF(L65<>"",L65-K65,IF(G65="Hecho","s/d",MAX(0,Avance!$B$2-K65)))) | P65: =IF(ISNUMBER(O65),ROUND(O65/7,1),O65) | Q65: =IF(J65="","No planificada",IF(G65="Hecho",IF(L65="","Hecha (sin fecha)",IF(L65>K65,"Hecha con atraso","Hecha a tiempo")),IF(Avance!$B$2>K65,"Pendiente atrasada","Pendiente en plazo"))) | R65: HT-01
A66: Sprint 7 | B66: QA / DevOps / Documentación | C66: Pruebas de aceptación interna (UAT) con datos reales de la maqueta, incluyendo el panel predictivo | D66: Equipo completo | E66: 3 | F66: Ambiente estable | G66: Por hacer | I66: Plan original | J66: =IF($I66="Plan original",INDEX('Roadmap Sprints'!$B$2:$B$9,MATCH(IF($A66="Cierre","Semana de cierre",$A66),'Roadmap Sprints'!$A$2:$A$9,0)),"") | K66: =IF($I66="Plan original",INDEX('Roadmap Sprints'!$C$2:$C$9,MATCH(IF($A66="Cierre","Semana de cierre",$A66),'Roadmap Sprints'!$A$2:$A$9,0)),"") | M66: =IF(J66="","",NETWORKDAYS(J66,K66)) | N66: =IF(J66="","",IF(L66<>"",IF(L66<J66,0,NETWORKDAYS(J66,L66)),IF(G66="Hecho","",IF(Avance!$B$2<J66,0,NETWORKDAYS(J66,Avance!$B$2))))) | O66: =IF(J66="","n/a",IF(L66<>"",L66-K66,IF(G66="Hecho","s/d",MAX(0,Avance!$B$2-K66)))) | P66: =IF(ISNUMBER(O66),ROUND(O66/7,1),O66) | Q66: =IF(J66="","No planificada",IF(G66="Hecho",IF(L66="","Hecha (sin fecha)",IF(L66>K66,"Hecha con atraso","Hecha a tiempo")),IF(Avance!$B$2>K66,"Pendiente atrasada","Pendiente en plazo"))) | R66: HT-04
A67: Sprint 7 | B67: Gestión de proyecto | C67: Preparar guion y datos de la demo para el cliente | D67: Equipo completo | E67: 2 | F67: UAT aprobado | G67: Por hacer | I67: Plan original | J67: =IF($I67="Plan original",INDEX('Roadmap Sprints'!$B$2:$B$9,MATCH(IF($A67="Cierre","Semana de cierre",$A67),'Roadmap Sprints'!$A$2:$A$9,0)),"") | K67: =IF($I67="Plan original",INDEX('Roadmap Sprints'!$C$2:$C$9,MATCH(IF($A67="Cierre","Semana de cierre",$A67),'Roadmap Sprints'!$A$2:$A$9,0)),"") | M67: =IF(J67="","",NETWORKDAYS(J67,K67)) | N67: =IF(J67="","",IF(L67<>"",IF(L67<J67,0,NETWORKDAYS(J67,L67)),IF(G67="Hecho","",IF(Avance!$B$2<J67,0,NETWORKDAYS(J67,Avance!$B$2))))) | O67: =IF(J67="","n/a",IF(L67<>"",L67-K67,IF(G67="Hecho","s/d",MAX(0,Avance!$B$2-K67)))) | P67: =IF(ISNUMBER(O67),ROUND(O67/7,1),O67) | Q67: =IF(J67="","No planificada",IF(G67="Hecho",IF(L67="","Hecha (sin fecha)",IF(L67>K67,"Hecha con atraso","Hecha a tiempo")),IF(Avance!$B$2>K67,"Pendiente atrasada","Pendiente en plazo"))) | R67: GE-01
A68: Sprint 7 | B68: Hardware / Sensores | C68: Preparar maqueta para transporte/instalación en el lugar de la demo | D68: Técnico | E68: 2 | F68: Maqueta estable | G68: Por hacer | I68: Plan original | J68: =IF($I68="Plan original",INDEX('Roadmap Sprints'!$B$2:$B$9,MATCH(IF($A68="Cierre","Semana de cierre",$A68),'Roadmap Sprints'!$A$2:$A$9,0)),"") | K68: =IF($I68="Plan original",INDEX('Roadmap Sprints'!$C$2:$C$9,MATCH(IF($A68="Cierre","Semana de cierre",$A68),'Roadmap Sprints'!$A$2:$A$9,0)),"") | M68: =IF(J68="","",NETWORKDAYS(J68,K68)) | N68: =IF(J68="","",IF(L68<>"",IF(L68<J68,0,NETWORKDAYS(J68,L68)),IF(G68="Hecho","",IF(Avance!$B$2<J68,0,NETWORKDAYS(J68,Avance!$B$2))))) | O68: =IF(J68="","n/a",IF(L68<>"",L68-K68,IF(G68="Hecho","s/d",MAX(0,Avance!$B$2-K68)))) | P68: =IF(ISNUMBER(O68),ROUND(O68/7,1),O68) | Q68: =IF(J68="","No planificada",IF(G68="Hecho",IF(L68="","Hecha (sin fecha)",IF(L68>K68,"Hecha con atraso","Hecha a tiempo")),IF(Avance!$B$2>K68,"Pendiente atrasada","Pendiente en plazo"))) | R68: HT-03
A69: Cierre | B69: QA / DevOps / Documentación | C69: Corrección de bugs críticos de última hora | D69: Equipo completo | E69: 2 | F69: Resultados de UAT | G69: Por hacer | I69: Plan original | J69: =IF($I69="Plan original",INDEX('Roadmap Sprints'!$B$2:$B$9,MATCH(IF($A69="Cierre","Semana de cierre",$A69),'Roadmap Sprints'!$A$2:$A$9,0)),"") | K69: =IF($I69="Plan original",INDEX('Roadmap Sprints'!$C$2:$C$9,MATCH(IF($A69="Cierre","Semana de cierre",$A69),'Roadmap Sprints'!$A$2:$A$9,0)),"") | M69: =IF(J69="","",NETWORKDAYS(J69,K69)) | N69: =IF(J69="","",IF(L69<>"",IF(L69<J69,0,NETWORKDAYS(J69,L69)),IF(G69="Hecho","",IF(Avance!$B$2<J69,0,NETWORKDAYS(J69,Avance!$B$2))))) | O69: =IF(J69="","n/a",IF(L69<>"",L69-K69,IF(G69="Hecho","s/d",MAX(0,Avance!$B$2-K69)))) | P69: =IF(ISNUMBER(O69),ROUND(O69/7,1),O69) | Q69: =IF(J69="","No planificada",IF(G69="Hecho",IF(L69="","Hecha (sin fecha)",IF(L69>K69,"Hecha con atraso","Hecha a tiempo")),IF(Avance!$B$2>K69,"Pendiente atrasada","Pendiente en plazo"))) | R69: HT-04
A70: Cierre | B70: Gestión de proyecto | C70: Ensayo general de la demo con equipo completo y maqueta | D70: Equipo completo | E70: 1 | F70: Guion de demo listo | G70: Por hacer | I70: Plan original | J70: =IF($I70="Plan original",INDEX('Roadmap Sprints'!$B$2:$B$9,MATCH(IF($A70="Cierre","Semana de cierre",$A70),'Roadmap Sprints'!$A$2:$A$9,0)),"") | K70: =IF($I70="Plan original",INDEX('Roadmap Sprints'!$C$2:$C$9,MATCH(IF($A70="Cierre","Semana de cierre",$A70),'Roadmap Sprints'!$A$2:$A$9,0)),"") | M70: =IF(J70="","",NETWORKDAYS(J70,K70)) | N70: =IF(J70="","",IF(L70<>"",IF(L70<J70,0,NETWORKDAYS(J70,L70)),IF(G70="Hecho","",IF(Avance!$B$2<J70,0,NETWORKDAYS(J70,Avance!$B$2))))) | O70: =IF(J70="","n/a",IF(L70<>"",L70-K70,IF(G70="Hecho","s/d",MAX(0,Avance!$B$2-K70)))) | P70: =IF(ISNUMBER(O70),ROUND(O70/7,1),O70) | Q70: =IF(J70="","No planificada",IF(G70="Hecho",IF(L70="","Hecha (sin fecha)",IF(L70>K70,"Hecha con atraso","Hecha a tiempo")),IF(Avance!$B$2>K70,"Pendiente atrasada","Pendiente en plazo"))) | R70: GE-01
A71: Cierre | B71: Gestión de proyecto | C71: Presentación del MVP al cliente (04-12-2026) | D71: Equipo completo | E71: 1 | F71: Ensayo aprobado | G71: Por hacer | I71: Plan original | J71: =IF($I71="Plan original",INDEX('Roadmap Sprints'!$B$2:$B$9,MATCH(IF($A71="Cierre","Semana de cierre",$A71),'Roadmap Sprints'!$A$2:$A$9,0)),"") | K71: =IF($I71="Plan original",INDEX('Roadmap Sprints'!$C$2:$C$9,MATCH(IF($A71="Cierre","Semana de cierre",$A71),'Roadmap Sprints'!$A$2:$A$9,0)),"") | M71: =IF(J71="","",NETWORKDAYS(J71,K71)) | N71: =IF(J71="","",IF(L71<>"",IF(L71<J71,0,NETWORKDAYS(J71,L71)),IF(G71="Hecho","",IF(Avance!$B$2<J71,0,NETWORKDAYS(J71,Avance!$B$2))))) | O71: =IF(J71="","n/a",IF(L71<>"",L71-K71,IF(G71="Hecho","s/d",MAX(0,Avance!$B$2-K71)))) | P71: =IF(ISNUMBER(O71),ROUND(O71/7,1),O71) | Q71: =IF(J71="","No planificada",IF(G71="Hecho",IF(L71="","Hecha (sin fecha)",IF(L71>K71,"Hecha con atraso","Hecha a tiempo")),IF(Avance!$B$2>K71,"Pendiente atrasada","Pendiente en plazo"))) | R71: GE-01
C73: Total estimado (días-persona) | E73: =SUM(E2:E71)
C74: del plan original | E74: =SUMIF(I2:I71,"Plan original",E2:E71)
C75: agregadas, no planificadas (estimación retroactiva) | E75: =SUMIF(I2:I71,"Agregada*",E2:E71)
C76: Nota: los días de las actividades agregadas son una estimación retroactiva hecha a partir del historial de git (18-oct-2026); confirmar con quien las realizó.
C77: Cómo leer el contraste plan vs. real (columnas J a Q):
C78: • Fin plan = último día del sprint donde se planificó la actividad (hoja 'Roadmap Sprints'). Las actividades agregadas no tienen compromiso, por eso figuran 'No planificada'.
C79: • Término real = fecha del commit o documento que evidencia que quedó hecha. Puede ser posterior al término verdadero (por ejemplo, un documento se subió después). En azul porque es un dato ingresado.
C80: • Días hábiles esperados = ventana del sprint (lunes a viernes). Días hábiles ejecutados = desde el inicio del sprint planificado hasta el término real o, si sigue pendiente, hasta la fecha de corte (Avance!B2).
C81: • Atraso = término real menos fin plan (negativo = se adelantó). Si sigue pendiente = fecha de corte menos fin plan, solo si ya pasó el compromiso. 's/d' = marcada Hecha sin fecha de evidencia.
C82: • No se descuentan feriados chilenos (igual que la hoja 'Roadmap Sprints').

Sheet Hitos
A1: Fecha | B1: Hito | C1: Descripción | D1: Días restantes desde hoy (24-08-2026)
A2: 46271 | B2: Cierre cotización + arquitectura + diseño ML | C2: Arquitectura Firebase aprobada, cotización de sensores finalizada y diseño de la simulación de datos para ML listo | D2: =A2-DATE(2026,8,24)
A3: 46285 | B3: Compra de sensores + primer modelo ML | C3: Orden de compra emitida, Authentication funcionando y primer modelo de ML entrenado con datos 100% simulados | D3: =A3-DATE(2026,8,24)
A4: 46299 | B4: Maqueta armada + ML integrado al backend | C4: Estructura física y sensores montados en la maqueta; modelo ML ya servido desde una Cloud Function | D4: =A4-DATE(2026,8,24)
A5: 46313 | B5: Primer end-to-end en vivo + panel predictivo inicial | C5: Datos reales de la maqueta visibles en el dashboard, con un primer panel de proyección ML (basado en datos simulados) | D5: =A5-DATE(2026,8,24)
A6: 46327 | B6: Visualización completa + ML usando datos reales | C6: Todas las variables clave visibles en tiempo real + históricos + modelos ML empezando a recalibrarse con datos reales | D6: =A6-DATE(2026,8,24)
A7: 46341 | B7: Seguridad y roles listos + ML validado | C7: Control de acceso por rol, reglas de seguridad aplicadas y modelos ML validados contra datos reales acumulados | D7: =A7-DATE(2026,8,24)
A8: 46355 | B8: MVP completo listo para UAT | C8: Ambiente de staging/producción estable, probado end-to-end, documentado y con UAT en curso | D8: =A8-DATE(2026,8,24)
A9: 46360 | B9: Presentación al cliente | C9: Demo oficial del MVP ante el cliente (fecha adelantada desde el 18-12 original) | D9: =A9-DATE(2026,8,24)

Sheet Riesgos
A1: Riesgo | B1: Categoría | C1: Probabilidad | D1: Impacto | E1: Mitigación
A2: Plazo de entrega de sensores/proveedores más largo de lo cotizado | B2: Hardware | C2: Alta | D2: Alto | E2: Cotizar y comprar en el Sprint 1-2 (lo antes posible); tener proveedor alternativo; usar datos simulados en paralelo para no bloquear el desarrollo de software
A3: Falla o descalibración de sensores durante pruebas | B3: Hardware | C3: Media | D3: Medio | E3: Comprar 1-2 sensores de respaldo por variable; calendarizar calibración en Sprint 4
A4: Conectividad inestable entre maqueta/gateway y Firebase | B4: Backend | C4: Media | D4: Alto | E4: Implementar manejo de reconexión y buffer local de datos en el gateway (Sprint 6)
A5: Sub-estimación del esfuerzo de visualización en tiempo real | B5: Frontend | C5: Media | D5: Medio | E5: Empezar con 1-2 variables en Sprint 4 antes de escalar a todas las variables en Sprint 5
A6: Cambios de alcance solicitados por el cliente durante el proyecto | B6: Gestión | C6: Alta | D6: Medio | E6: Backlog priorizado y revisiones de sprint (sprint review) con el cliente para validar alcance a tiempo
A7: Sobrecarga del técnico (única persona a cargo de la maqueta) | B7: Equipo | C7: Media | D7: Alto | E7: Involucrar a un desarrollador de apoyo en tareas simples de hardware; planificar holguras en Sprints 3 y 6
A8: Fecha de demo fija (04-12-2026), adelantada 2 semanas respecto al plazo original, sin margen real de atraso | B8: Gestión | C8: Alta | D8: Alto | E8: El cronograma pasó de 8 a 7 sprints manteniendo el mismo alcance (incluido ML); la semana de cierre (30 nov-4 dic) es ahora el único colchón real, no un buffer adicional; congelar todo alcance nuevo desde el Sprint 6 y revisar avance real vs. plan en cada sprint review
A9: No existen datos históricos reales para entrenar los modelos de ML clásico | B9: Datos / Analítica | C9: Alta | D9: Alto | E9: Usar datos simulados/sintéticos física-informados desde el Sprint 1-2 para entrenar y probar los modelos (regresión / ARIMA-Prophet); recalibrarlos progresivamente con datos reales de la maqueta desde el Sprint 3-5; ser transparentes con el cliente en la demo sobre que el modelo mejora su precisión con más datos reales de uso
A10: El análisis predictivo con ML clásico agrega alcance nuevo sin que se haya ampliado el plazo ni el equipo (y encima el plazo se acortó) | B10: Gestión | C10: Alta | D10: Alto | E10: Mantener el ML acotado a modelos clásicos simples (regresión/series de tiempo), nunca deep learning; si se atrasa, priorizarlo sobre pulido de UI secundario o históricos extendidos, nunca sobre el pipeline de datos en tiempo real que es el core del MVP; evaluar en el sprint review de Sprint 4 si el ritmo real permite sostener el alcance completo o si hay que recortar

Sheet Análisis Predictivo
A1: Análisis predictivo del MVP – enfoque recomendado (ML clásico)
A2: Sin datos históricos reales al día de hoy (24-08-2026): se entrena con datos simulados desde el inicio y se recalibra con datos reales de la maqueta a medida que se acumulan. Plazo comprimido al 04-12-2026.
A4: Decisión de alcance
A5: Qué SÍ entra en el MVP | B5: Análisis predictivo con Machine Learning clásico: modelos de regresión y/o series de tiempo (ARIMA, Prophet) para proyectar cuándo se agotará el stock de un químico o el consumo de agua según el ritmo actual, y modelos de detección de anomalías/tendencia (ej. umbrales dinámicos, Isolation Forest) para alertar cuando una variable (pH, temperatura, conductividad) muestra una tendencia hacia fuera de rango.
A7: Por qué ML clásico y no deep learning | B7: Un modelo de deep learning (redes neuronales, LSTM) necesita mucho más volumen de datos reales, tiempo de tuning e infraestructura adicional (Firebase Functions es Node.js; un modelo Python probablemente requiera Cloud Run o Vertex AI aparte) de lo que el cronograma permite, más aún tras acortarse a 04-12. Los modelos de ML clásico son livianos de entrenar, se pueden servir fácilmente desde el backend, y dan una demo creíble sin ese costo de tiempo.
A9: Qué NO entra en el MVP | B9: Modelos de deep learning (redes neuronales, LSTM, clasificación de fallas avanzada, mantenimiento predictivo). Quedan como evolución natural del producto una vez que la maqueta/planta acumule datos reales de varios meses.
A11: Impacto del plazo adelantado (04-12 en vez de 18-12) | B11: El módulo de ML se mueve al inicio del proyecto (diseño en Sprint 1, dataset simulado y primer entrenamiento en Sprint 2) para que la recalibración con datos reales pueda empezar apenas la maqueta entregue sus primeras lecturas (Sprint 5), en vez de esperar a los últimos sprints como en el plan original.
A14: Plan de datos por etapa
A15: Etapa | B15: Origen de los datos | C15: Qué permite hacer
A16: Sprint 1 (24 ago–6 sep) | B16: Ninguno todavía — se diseña qué y cómo simular (variables, rangos, patrones física-informados de un ciclo CIP) | C16: Dejar un diseño de simulación validado por el equipo antes de escribir código de ML
A17: Sprint 2 (7–20 sep) | B17: Dataset 100% simulado/sintético (generado en Python según el diseño del Sprint 1) | C17: Entrenar la primera versión de los modelos de ML clásico (regresión / ARIMA-Prophet) sin quedar bloqueados esperando la maqueta
A18: Sprint 3-4 (21 sep–18 oct) | B18: Dataset simulado + primeras lecturas reales puntuales de la maqueta | C18: Integrar el modelo al backend (Cloud Function) y mostrar un primer panel predictivo en el dashboard, aunque el modelo aún esté entrenado solo con datos simulados
A19: Sprint 5 (19 oct–1 nov) | B19: Datos reales acumulados de las primeras 1-2 semanas de la maqueta funcionando | C19: Empezar a recalibrar/re-entrenar los modelos con datos reales en vez de solo simulados
A20: Sprint 6 (2–15 nov) | B20: Datos reales acumulados de ~4-5 semanas de la maqueta | C20: Validar si las proyecciones/alertas tienen sentido frente a lo que realmente ocurrió, y ajustar
A21: Sprint 7 y cierre (16 nov–4 dic) | B21: Datos reales + fallback a datos simulados extendidos solo para completar el rango visual en la demo, dejándolo explícito en el guion | C21: Presentar el panel predictivo de forma creíble sin prometer al cliente una precisión que un histórico de meses no puede sustentar aún
A23: Qué mostrar en la demo del 04-12
A24: • | B24: Proyección de consumo (regresión / series de tiempo): 'al ritmo actual, el químico X se agota en aproximadamente N días'.
A25: • | B25: Alerta de tendencia (detección de anomalías): 'la conductividad viene subiendo en las últimas horas y podría salir de rango si continúa así'.
A26: • | B26: Ser transparentes con el cliente sobre que el modelo se entrenó con datos simulados y reales de la maqueta, y que mejora su precisión a medida que se acumulen más datos reales de uso en planta.
